{
  "id": "iran_israel",
  "name": "Irán–Israel/EE.UU.",
  "description": "Cobertura mediática del conflicto entre Irán, Israel y Estados Unidos",
  "updated": "2026-07-12T19:31:20+00:00",
  "total_articles": 2070,
  "overall_avg": -0.2999,
  "distribution": {
    "pos": 475,
    "neu": 321,
    "neg": 1274
  },
  "sources": [
    "Al Jazeera",
    "Times of Israel",
    "BBC",
    "The Times of Israel",
    "NPR",
    "The Guardian",
    "The Jerusalem Post",
    "Reuters",
    "Crypto Briefing",
    "The New York Times",
    "Haaretz",
    "Ynetnews",
    "JNS.org",
    "NBC News",
    "Israel National News",
    "The Independent",
    "NDTV",
    "PBS",
    "AP News",
    "Fox News",
    "The Hill",
    "i24NEWS",
    "CBS News",
    "The Times of India",
    "www.israelhayom.com",
    "JNS",
    "Middle East Monitor",
    "Yahoo",
    "CNN",
    "The Washington Post",
    "France 24",
    "New York Post",
    "ایران اینترنشنال",
    "Jewish Telegraphic Agency",
    "Al-Monitor",
    "Asharq Al-Awsat English",
    "thenationalnews.com",
    "Anadolu Ajansı",
    "The New Arab",
    "National Desk",
    "Middle East Eye",
    "CBC",
    "Al Arabiya English",
    "EA WorldView",
    "The Christian Science Monitor",
    "Council on Foreign Relations",
    "Axios",
    "Time Magazine",
    "Washington Times",
    "Muslim Network TV",
    "Українські Національні Новини (УНН)",
    "The Federal",
    "ABC News - Breaking News, Latest News and Videos",
    "middle-east-online.com",
    "WION",
    "DW.com",
    "Deccan Herald",
    "Washington Examiner",
    "AOL.com",
    "The Hindu",
    "Sky News",
    "arabnews.jp",
    "CTech",
    "اسلام تايمز",
    "Kurdistan24",
    "Foreign Policy",
    "IranWire",
    "TheWire.in",
    "Egypt Independent",
    "Travel And Tour World",
    "The Indian Express",
    "CNBC",
    "KCRA",
    "Latest news from Azerbaijan",
    "The Conversation",
    "The Forward",
    "KSNV",
    "Caspianpost.com",
    "Межа. Новини України.",
    "تسنیم",
    "Benzinga",
    "The Media Line",
    "Manara Magazine",
    "The Pittsburgh Jewish Chronicle",
    "cbn.com",
    "Arab News",
    "UA.NEWS",
    "WSJ",
    "MS NOW",
    "Open Magazine",
    "Audacy",
    "The Telegraph",
    "Radio Free Europe/Radio Liberty",
    "Truthout",
    "NewsNation",
    "+972 Magazine",
    "Euronews",
    "Encyclopedia Britannica",
    "Mother Jones",
    "Boston Herald",
    "kmph.com",
    "vox.com",
    "TRT World",
    "WTAE",
    "CSIS | Center for Strategic and International Studies",
    "The Economist",
    "NonStop Local Billings",
    "The New Yorker",
    "Arab News PK",
    "WDSU",
    "Military.com",
    "Middle East Forum",
    "The Washington Stand",
    "Begin-Sadat Center for Strategic Studies",
    "Türkiye Today",
    "Alma Research and Education Center",
    "PennLive.com",
    "6abc Philadelphia",
    "The Globe and Mail",
    "The Diplomatic Insight",
    "Plataforma Media",
    "The New Region",
    "bastillepost.com",
    "CairoScene",
    "WTVC",
    "WJAR",
    "National Herald",
    "Common Dreams",
    "The Business Standard",
    "Modern Ghana",
    "ABC7 Los Angeles",
    "Pajhwok Afghan News",
    "Salon.com",
    "Dawn",
    "KFOX",
    "L'Orient Today",
    "Informed Comment",
    "TV7 Israel News",
    "Infosecurity Magazine",
    "FOX4KC.com",
    "Politico",
    "Le Monde.fr",
    "The New York Sun",
    "PNI Atlantic News",
    "EFE - Agencia de noticias",
    "Jewish Insider",
    "Christianity Today",
    "The Israel Democracy Institute",
    "camera.org",
    "The American Conservative",
    "U.S. News & World Report",
    "Drop Site News",
    "FOX40",
    "Forth.News",
    "Forbes",
    "Democracy Now!",
    "GV Wire",
    "The Irish Times",
    "WDEF",
    "Yahoo News Australia",
    "The Salt Lake Tribune",
    "الحرة",
    "iranpress.com",
    "Investing.com Nigeria",
    "Quincy Institute for Responsible Statecraft",
    "Defense Priorities",
    "Baird Maritime",
    "Military Watch Magazine",
    "Brookings",
    "Small Wars Journal",
    "WPDE",
    "The Lufkin Daily News",
    "Center for International Policy",
    "Shoreline Media Group",
    "jewishaz.com",
    "Foundation for Defense of Democracies",
    "ABC News & Headlines – Australian Broadcasting Corporation",
    "The Spectator",
    "Eurasia Review",
    "Il Sole 24 ORE",
    "KATU",
    "KHOU",
    "WesternSlopeNow.com",
    "Yahoo News Canada",
    "KABB",
    "KFXL",
    "Kyiv Post",
    "KGAN",
    "CNA",
    "شفق نيوز",
    "AnewZ",
    "KTLA",
    "thecradle.co",
    "connectedtoindia.com",
    "The Express Tribune",
    "Scripps News",
    "FOX 29 Philadelphia",
    "Japan Wire by Kyodo News",
    "FOX 9 Minneapolis-St. Paul",
    "AzerNews",
    "La Voce di New York",
    "Newser",
    "UN News",
    "Arab Center Washington DC",
    "IFCJ",
    "South China Morning Post",
    "10News.com",
    "news8000.com",
    "Українські Новини",
    "Zeteo",
    "Xinhua",
    "NewsCord",
    "chinadailyasia.com",
    "Denver Gazette",
    "WOAI",
    "Tehran Times",
    "Firstpost",
    "WFLA",
    "FOX21 News Colorado",
    "WGN-TV",
    "WKU Public Radio",
    "Financial Times",
    "C-SPAN",
    "ABC7 Chicago",
    "조선일보"
  ],
  "daily": [
    {
      "date": "2026-05-18",
      "count": 1,
      "avg": -0.9628,
      "pos": 0,
      "neu": 0,
      "neg": 1
    },
    {
      "date": "2026-05-19",
      "count": 1,
      "avg": -0.8316,
      "pos": 0,
      "neu": 0,
      "neg": 1
    },
    {
      "date": "2026-05-20",
      "count": 1,
      "avg": 0.0,
      "pos": 0,
      "neu": 1,
      "neg": 0
    },
    {
      "date": "2026-05-23",
      "count": 1,
      "avg": 0.0,
      "pos": 0,
      "neu": 1,
      "neg": 0
    },
    {
      "date": "2026-05-24",
      "count": 3,
      "avg": -0.3446,
      "pos": 0,
      "neu": 1,
      "neg": 2
    },
    {
      "date": "2026-05-25",
      "count": 2,
      "avg": -0.1366,
      "pos": 1,
      "neu": 0,
      "neg": 1
    },
    {
      "date": "2026-05-27",
      "count": 3,
      "avg": -0.6172,
      "pos": 0,
      "neu": 1,
      "neg": 2
    },
    {
      "date": "2026-05-28",
      "count": 1,
      "avg": 0.8402,
      "pos": 1,
      "neu": 0,
      "neg": 0
    },
    {
      "date": "2026-06-01",
      "count": 5,
      "avg": -0.3723,
      "pos": 0,
      "neu": 1,
      "neg": 4
    },
    {
      "date": "2026-06-02",
      "count": 4,
      "avg": -0.2279,
      "pos": 1,
      "neu": 1,
      "neg": 2
    },
    {
      "date": "2026-06-03",
      "count": 1,
      "avg": 0.4939,
      "pos": 1,
      "neu": 0,
      "neg": 0
    },
    {
      "date": "2026-06-05",
      "count": 1,
      "avg": -0.9732,
      "pos": 0,
      "neu": 0,
      "neg": 1
    },
    {
      "date": "2026-06-06",
      "count": 1,
      "avg": -0.8625,
      "pos": 0,
      "neu": 0,
      "neg": 1
    },
    {
      "date": "2026-06-07",
      "count": 2,
      "avg": -0.7778,
      "pos": 0,
      "neu": 0,
      "neg": 2
    },
    {
      "date": "2026-06-08",
      "count": 4,
      "avg": -0.6419,
      "pos": 0,
      "neu": 1,
      "neg": 3
    },
    {
      "date": "2026-06-09",
      "count": 1,
      "avg": -0.8316,
      "pos": 0,
      "neu": 0,
      "neg": 1
    },
    {
      "date": "2026-06-10",
      "count": 2,
      "avg": -0.7699,
      "pos": 0,
      "neu": 0,
      "neg": 2
    },
    {
      "date": "2026-06-11",
      "count": 1,
      "avg": -0.8316,
      "pos": 0,
      "neu": 0,
      "neg": 1
    },
    {
      "date": "2026-06-12",
      "count": 1,
      "avg": -0.6808,
      "pos": 0,
      "neu": 0,
      "neg": 1
    },
    {
      "date": "2026-06-14",
      "count": 5,
      "avg": -0.1237,
      "pos": 2,
      "neu": 1,
      "neg": 2
    },
    {
      "date": "2026-06-15",
      "count": 4,
      "avg": -0.1656,
      "pos": 2,
      "neu": 0,
      "neg": 2
    },
    {
      "date": "2026-06-16",
      "count": 4,
      "avg": -0.8085,
      "pos": 0,
      "neu": 0,
      "neg": 4
    },
    {
      "date": "2026-06-17",
      "count": 2,
      "avg": -0.8073,
      "pos": 0,
      "neu": 0,
      "neg": 2
    },
    {
      "date": "2026-06-18",
      "count": 1,
      "avg": -0.2023,
      "pos": 0,
      "neu": 0,
      "neg": 1
    },
    {
      "date": "2026-06-19",
      "count": 8,
      "avg": -0.0829,
      "pos": 3,
      "neu": 1,
      "neg": 4
    },
    {
      "date": "2026-06-20",
      "count": 3,
      "avg": -0.2594,
      "pos": 0,
      "neu": 2,
      "neg": 1
    },
    {
      "date": "2026-06-21",
      "count": 3,
      "avg": -0.349,
      "pos": 1,
      "neu": 0,
      "neg": 2
    },
    {
      "date": "2026-06-22",
      "count": 3,
      "avg": -0.2907,
      "pos": 1,
      "neu": 0,
      "neg": 2
    },
    {
      "date": "2026-06-23",
      "count": 1,
      "avg": -0.9042,
      "pos": 0,
      "neu": 0,
      "neg": 1
    },
    {
      "date": "2026-06-24",
      "count": 2,
      "avg": -0.8945,
      "pos": 0,
      "neu": 0,
      "neg": 2
    },
    {
      "date": "2026-06-25",
      "count": 5,
      "avg": -0.3106,
      "pos": 1,
      "neu": 1,
      "neg": 3
    },
    {
      "date": "2026-06-26",
      "count": 5,
      "avg": -0.5641,
      "pos": 0,
      "neu": 1,
      "neg": 4
    },
    {
      "date": "2026-06-27",
      "count": 3,
      "avg": -0.6499,
      "pos": 0,
      "neu": 0,
      "neg": 3
    },
    {
      "date": "2026-06-28",
      "count": 8,
      "avg": -0.6889,
      "pos": 1,
      "neu": 0,
      "neg": 7
    },
    {
      "date": "2026-06-29",
      "count": 5,
      "avg": -0.3903,
      "pos": 1,
      "neu": 0,
      "neg": 4
    },
    {
      "date": "2026-06-30",
      "count": 3,
      "avg": -0.0355,
      "pos": 2,
      "neu": 0,
      "neg": 1
    },
    {
      "date": "2026-07-01",
      "count": 3,
      "avg": -0.6743,
      "pos": 0,
      "neu": 0,
      "neg": 3
    },
    {
      "date": "2026-07-02",
      "count": 14,
      "avg": -0.4687,
      "pos": 2,
      "neu": 2,
      "neg": 10
    },
    {
      "date": "2026-07-03",
      "count": 40,
      "avg": -0.4683,
      "pos": 7,
      "neu": 2,
      "neg": 31
    },
    {
      "date": "2026-07-04",
      "count": 110,
      "avg": -0.2878,
      "pos": 26,
      "neu": 16,
      "neg": 68
    },
    {
      "date": "2026-07-05",
      "count": 183,
      "avg": -0.2302,
      "pos": 47,
      "neu": 29,
      "neg": 107
    },
    {
      "date": "2026-07-06",
      "count": 247,
      "avg": -0.2358,
      "pos": 68,
      "neu": 45,
      "neg": 134
    },
    {
      "date": "2026-07-07",
      "count": 218,
      "avg": -0.2572,
      "pos": 57,
      "neu": 39,
      "neg": 122
    },
    {
      "date": "2026-07-08",
      "count": 297,
      "avg": -0.3565,
      "pos": 56,
      "neu": 42,
      "neg": 199
    },
    {
      "date": "2026-07-09",
      "count": 260,
      "avg": -0.3004,
      "pos": 66,
      "neu": 28,
      "neg": 166
    },
    {
      "date": "2026-07-10",
      "count": 296,
      "avg": -0.3384,
      "pos": 56,
      "neu": 44,
      "neg": 196
    },
    {
      "date": "2026-07-11",
      "count": 147,
      "avg": -0.2491,
      "pos": 39,
      "neu": 24,
      "neg": 84
    },
    {
      "date": "2026-07-12",
      "count": 154,
      "avg": -0.2736,
      "pos": 33,
      "neu": 37,
      "neg": 84
    }
  ],
  "by_source": [
    {
      "source": "Al Jazeera",
      "count": 736,
      "avg": -0.2365
    },
    {
      "source": "Times of Israel",
      "count": 262,
      "avg": -0.2903
    },
    {
      "source": "BBC",
      "count": 209,
      "avg": -0.1908
    },
    {
      "source": "The Times of Israel",
      "count": 99,
      "avg": -0.3278
    },
    {
      "source": "NPR",
      "count": 75,
      "avg": -0.3028
    },
    {
      "source": "The Guardian",
      "count": 74,
      "avg": -0.5555
    },
    {
      "source": "The Jerusalem Post",
      "count": 49,
      "avg": -0.2458
    },
    {
      "source": "Reuters",
      "count": 23,
      "avg": -0.3122
    },
    {
      "source": "Crypto Briefing",
      "count": 16,
      "avg": -0.5043
    },
    {
      "source": "The New York Times",
      "count": 15,
      "avg": -0.3988
    },
    {
      "source": "Haaretz",
      "count": 15,
      "avg": -0.477
    },
    {
      "source": "Ynetnews",
      "count": 14,
      "avg": -0.738
    },
    {
      "source": "JNS.org",
      "count": 13,
      "avg": -0.1963
    },
    {
      "source": "NBC News",
      "count": 12,
      "avg": -0.6452
    },
    {
      "source": "Israel National News",
      "count": 11,
      "avg": -0.3026
    },
    {
      "source": "The Independent",
      "count": 10,
      "avg": -0.6275
    },
    {
      "source": "NDTV",
      "count": 10,
      "avg": -0.7341
    },
    {
      "source": "PBS",
      "count": 10,
      "avg": -0.1742
    },
    {
      "source": "AP News",
      "count": 10,
      "avg": -0.4712
    },
    {
      "source": "Fox News",
      "count": 10,
      "avg": -0.3085
    },
    {
      "source": "The Hill",
      "count": 9,
      "avg": -0.7161
    },
    {
      "source": "i24NEWS",
      "count": 9,
      "avg": -0.5956
    },
    {
      "source": "CBS News",
      "count": 9,
      "avg": -0.2016
    },
    {
      "source": "The Times of India",
      "count": 9,
      "avg": -0.3075
    },
    {
      "source": "www.israelhayom.com",
      "count": 8,
      "avg": -0.6301
    },
    {
      "source": "JNS",
      "count": 8,
      "avg": 0.0348
    },
    {
      "source": "Middle East Monitor",
      "count": 8,
      "avg": -0.212
    },
    {
      "source": "Yahoo",
      "count": 8,
      "avg": -0.3649
    },
    {
      "source": "CNN",
      "count": 7,
      "avg": 0.0022
    },
    {
      "source": "The Washington Post",
      "count": 7,
      "avg": -0.2275
    },
    {
      "source": "France 24",
      "count": 7,
      "avg": -0.4543
    },
    {
      "source": "New York Post",
      "count": 7,
      "avg": -0.0034
    },
    {
      "source": "ایران اینترنشنال",
      "count": 6,
      "avg": -0.2679
    },
    {
      "source": "Jewish Telegraphic Agency",
      "count": 6,
      "avg": 0.0291
    },
    {
      "source": "Al-Monitor",
      "count": 6,
      "avg": -0.2334
    },
    {
      "source": "Asharq Al-Awsat English",
      "count": 5,
      "avg": -0.3315
    },
    {
      "source": "thenationalnews.com",
      "count": 5,
      "avg": -0.3184
    },
    {
      "source": "Anadolu Ajansı",
      "count": 4,
      "avg": -0.5358
    },
    {
      "source": "The New Arab",
      "count": 4,
      "avg": -0.1606
    },
    {
      "source": "National Desk",
      "count": 4,
      "avg": -0.58
    },
    {
      "source": "Middle East Eye",
      "count": 4,
      "avg": -0.3022
    },
    {
      "source": "CBC",
      "count": 4,
      "avg": -0.2276
    },
    {
      "source": "Al Arabiya English",
      "count": 4,
      "avg": -0.3301
    },
    {
      "source": "EA WorldView",
      "count": 3,
      "avg": -0.7804
    },
    {
      "source": "The Christian Science Monitor",
      "count": 3,
      "avg": -0.4201
    },
    {
      "source": "Council on Foreign Relations",
      "count": 3,
      "avg": -0.2594
    },
    {
      "source": "Axios",
      "count": 3,
      "avg": -0.2807
    },
    {
      "source": "Time Magazine",
      "count": 3,
      "avg": 0.3293
    },
    {
      "source": "Washington Times",
      "count": 3,
      "avg": 0.2441
    },
    {
      "source": "Muslim Network TV",
      "count": 3,
      "avg": -0.393
    },
    {
      "source": "Українські Національні Новини (УНН)",
      "count": 3,
      "avg": 0.2645
    },
    {
      "source": "The Federal",
      "count": 3,
      "avg": -0.6625
    },
    {
      "source": "ABC News - Breaking News, Latest News and Videos",
      "count": 3,
      "avg": -0.8104
    },
    {
      "source": "middle-east-online.com",
      "count": 3,
      "avg": -0.3425
    },
    {
      "source": "WION",
      "count": 3,
      "avg": -0.8087
    },
    {
      "source": "DW.com",
      "count": 3,
      "avg": -0.5792
    },
    {
      "source": "Deccan Herald",
      "count": 3,
      "avg": -0.0176
    },
    {
      "source": "Washington Examiner",
      "count": 3,
      "avg": -0.2418
    },
    {
      "source": "AOL.com",
      "count": 3,
      "avg": 0.0491
    },
    {
      "source": "The Hindu",
      "count": 3,
      "avg": -0.5622
    },
    {
      "source": "Sky News",
      "count": 3,
      "avg": -0.943
    },
    {
      "source": "arabnews.jp",
      "count": 2,
      "avg": -0.6001
    },
    {
      "source": "CTech",
      "count": 2,
      "avg": -0.5433
    },
    {
      "source": "اسلام تايمز",
      "count": 2,
      "avg": -0.9475
    },
    {
      "source": "Kurdistan24",
      "count": 2,
      "avg": -0.9001
    },
    {
      "source": "Foreign Policy",
      "count": 2,
      "avg": -0.3675
    },
    {
      "source": "IranWire",
      "count": 2,
      "avg": -0.3891
    },
    {
      "source": "TheWire.in",
      "count": 2,
      "avg": -0.8788
    },
    {
      "source": "Egypt Independent",
      "count": 2,
      "avg": -0.8584
    },
    {
      "source": "Travel And Tour World",
      "count": 2,
      "avg": -0.0455
    },
    {
      "source": "The Indian Express",
      "count": 2,
      "avg": -0.9508
    },
    {
      "source": "CNBC",
      "count": 2,
      "avg": -0.1737
    },
    {
      "source": "KCRA",
      "count": 2,
      "avg": -0.6815
    },
    {
      "source": "Latest news from Azerbaijan",
      "count": 2,
      "avg": -0.7343
    },
    {
      "source": "The Conversation",
      "count": 2,
      "avg": -0.3891
    },
    {
      "source": "The Forward",
      "count": 2,
      "avg": 0.4884
    },
    {
      "source": "KSNV",
      "count": 2,
      "avg": -0.3119
    },
    {
      "source": "Caspianpost.com",
      "count": 2,
      "avg": 0.0691
    },
    {
      "source": "Межа. Новини України.",
      "count": 2,
      "avg": -0.8198
    },
    {
      "source": "تسنیم",
      "count": 2,
      "avg": -0.7788
    },
    {
      "source": "Benzinga",
      "count": 2,
      "avg": -0.2804
    },
    {
      "source": "The Media Line",
      "count": 2,
      "avg": -0.6361
    },
    {
      "source": "Manara Magazine",
      "count": 2,
      "avg": 0.0
    },
    {
      "source": "The Pittsburgh Jewish Chronicle",
      "count": 2,
      "avg": 0.0
    },
    {
      "source": "cbn.com",
      "count": 2,
      "avg": -0.7015
    },
    {
      "source": "Arab News",
      "count": 2,
      "avg": -0.296
    },
    {
      "source": "UA.NEWS",
      "count": 2,
      "avg": 0.3125
    },
    {
      "source": "WSJ",
      "count": 2,
      "avg": -0.7814
    },
    {
      "source": "MS NOW",
      "count": 2,
      "avg": -0.4313
    },
    {
      "source": "Open Magazine",
      "count": 2,
      "avg": -0.9183
    },
    {
      "source": "Audacy",
      "count": 2,
      "avg": -0.9042
    },
    {
      "source": "The Telegraph",
      "count": 2,
      "avg": -0.3185
    },
    {
      "source": "Radio Free Europe/Radio Liberty",
      "count": 1,
      "avg": 0.7579
    },
    {
      "source": "Truthout",
      "count": 1,
      "avg": 0.7906
    },
    {
      "source": "NewsNation",
      "count": 1,
      "avg": -0.3818
    },
    {
      "source": "+972 Magazine",
      "count": 1,
      "avg": -0.8316
    },
    {
      "source": "Euronews",
      "count": 1,
      "avg": 0.0
    },
    {
      "source": "Encyclopedia Britannica",
      "count": 1,
      "avg": -0.7783
    },
    {
      "source": "Mother Jones",
      "count": 1,
      "avg": 0.7003
    },
    {
      "source": "Boston Herald",
      "count": 1,
      "avg": -0.6124
    },
    {
      "source": "kmph.com",
      "count": 1,
      "avg": -0.8481
    },
    {
      "source": "vox.com",
      "count": 1,
      "avg": 0.0
    },
    {
      "source": "TRT World",
      "count": 1,
      "avg": 0.1531
    },
    {
      "source": "WTAE",
      "count": 1,
      "avg": -0.7506
    },
    {
      "source": "CSIS | Center for Strategic and International Studies",
      "count": 1,
      "avg": 0.0
    },
    {
      "source": "The Economist",
      "count": 1,
      "avg": 0.6072
    },
    {
      "source": "NonStop Local Billings",
      "count": 1,
      "avg": -0.4939
    },
    {
      "source": "The New Yorker",
      "count": 1,
      "avg": -0.8481
    },
    {
      "source": "Arab News PK",
      "count": 1,
      "avg": 0.7351
    },
    {
      "source": "WDSU",
      "count": 1,
      "avg": -0.7506
    },
    {
      "source": "Military.com",
      "count": 1,
      "avg": 0.0
    },
    {
      "source": "Middle East Forum",
      "count": 1,
      "avg": 0.7741
    },
    {
      "source": "The Washington Stand",
      "count": 1,
      "avg": -0.7351
    },
    {
      "source": "Begin-Sadat Center for Strategic Studies",
      "count": 1,
      "avg": 0.0
    },
    {
      "source": "Türkiye Today",
      "count": 1,
      "avg": -0.8481
    },
    {
      "source": "Alma Research and Education Center",
      "count": 1,
      "avg": 0.0
    },
    {
      "source": "PennLive.com",
      "count": 1,
      "avg": 0.0
    },
    {
      "source": "6abc Philadelphia",
      "count": 1,
      "avg": -0.8957
    },
    {
      "source": "The Globe and Mail",
      "count": 1,
      "avg": -0.8402
    },
    {
      "source": "The Diplomatic Insight",
      "count": 1,
      "avg": -0.7003
    },
    {
      "source": "Plataforma Media",
      "count": 1,
      "avg": 0.0
    },
    {
      "source": "The New Region",
      "count": 1,
      "avg": -0.6369
    },
    {
      "source": "bastillepost.com",
      "count": 1,
      "avg": 0.0
    },
    {
      "source": "CairoScene",
      "count": 1,
      "avg": -0.8316
    },
    {
      "source": "WTVC",
      "count": 1,
      "avg": -0.8481
    },
    {
      "source": "WJAR",
      "count": 1,
      "avg": -0.8481
    },
    {
      "source": "National Herald",
      "count": 1,
      "avg": -0.8316
    },
    {
      "source": "Common Dreams",
      "count": 1,
      "avg": 0.836
    },
    {
      "source": "The Business Standard",
      "count": 1,
      "avg": 0.34
    },
    {
      "source": "Modern Ghana",
      "count": 1,
      "avg": -0.6124
    },
    {
      "source": "ABC7 Los Angeles",
      "count": 1,
      "avg": -0.8957
    },
    {
      "source": "Pajhwok Afghan News",
      "count": 1,
      "avg": -0.5267
    },
    {
      "source": "Salon.com",
      "count": 1,
      "avg": -0.7506
    },
    {
      "source": "Dawn",
      "count": 1,
      "avg": -0.9153
    },
    {
      "source": "KFOX",
      "count": 1,
      "avg": -0.8481
    },
    {
      "source": "L'Orient Today",
      "count": 1,
      "avg": 0.6808
    },
    {
      "source": "Informed Comment",
      "count": 1,
      "avg": -0.8676
    },
    {
      "source": "TV7 Israel News",
      "count": 1,
      "avg": -0.9451
    },
    {
      "source": "Infosecurity Magazine",
      "count": 1,
      "avg": 0.0
    },
    {
      "source": "FOX4KC.com",
      "count": 1,
      "avg": -0.34
    },
    {
      "source": "Politico",
      "count": 1,
      "avg": 0.0
    },
    {
      "source": "Le Monde.fr",
      "count": 1,
      "avg": 0.0
    },
    {
      "source": "The New York Sun",
      "count": 1,
      "avg": -0.8126
    },
    {
      "source": "PNI Atlantic News",
      "count": 1,
      "avg": 0.0
    },
    {
      "source": "EFE - Agencia de noticias",
      "count": 1,
      "avg": -0.1531
    },
    {
      "source": "Jewish Insider",
      "count": 1,
      "avg": 0.7506
    },
    {
      "source": "Christianity Today",
      "count": 1,
      "avg": -0.9325
    },
    {
      "source": "The Israel Democracy Institute",
      "count": 1,
      "avg": 0.2023
    },
    {
      "source": "camera.org",
      "count": 1,
      "avg": -0.5267
    },
    {
      "source": "The American Conservative",
      "count": 1,
      "avg": -0.0516
    },
    {
      "source": "U.S. News & World Report",
      "count": 1,
      "avg": 0.0
    },
    {
      "source": "Drop Site News",
      "count": 1,
      "avg": -0.9643
    },
    {
      "source": "FOX40",
      "count": 1,
      "avg": -0.34
    },
    {
      "source": "Forth.News",
      "count": 1,
      "avg": -0.6124
    },
    {
      "source": "Forbes",
      "count": 1,
      "avg": 0.0
    },
    {
      "source": "Democracy Now!",
      "count": 1,
      "avg": 0.0
    },
    {
      "source": "GV Wire",
      "count": 1,
      "avg": -0.886
    },
    {
      "source": "The Irish Times",
      "count": 1,
      "avg": -0.9274
    },
    {
      "source": "WDEF",
      "count": 1,
      "avg": -0.7351
    },
    {
      "source": "Yahoo News Australia",
      "count": 1,
      "avg": -0.4215
    },
    {
      "source": "The Salt Lake Tribune",
      "count": 1,
      "avg": -0.25
    },
    {
      "source": "الحرة",
      "count": 1,
      "avg": 0.0
    },
    {
      "source": "iranpress.com",
      "count": 1,
      "avg": -0.8225
    },
    {
      "source": "Investing.com Nigeria",
      "count": 1,
      "avg": 0.0
    },
    {
      "source": "Quincy Institute for Responsible Statecraft",
      "count": 1,
      "avg": 0.3182
    },
    {
      "source": "Defense Priorities",
      "count": 1,
      "avg": 0.128
    },
    {
      "source": "Baird Maritime",
      "count": 1,
      "avg": -0.4939
    },
    {
      "source": "Military Watch Magazine",
      "count": 1,
      "avg": 0.7003
    },
    {
      "source": "Brookings",
      "count": 1,
      "avg": -0.8481
    },
    {
      "source": "Small Wars Journal",
      "count": 1,
      "avg": -0.941
    },
    {
      "source": "WPDE",
      "count": 1,
      "avg": -0.4215
    },
    {
      "source": "The Lufkin Daily News",
      "count": 1,
      "avg": -0.7003
    },
    {
      "source": "Center for International Policy",
      "count": 1,
      "avg": -0.6124
    },
    {
      "source": "Shoreline Media Group",
      "count": 1,
      "avg": -0.7003
    },
    {
      "source": "jewishaz.com",
      "count": 1,
      "avg": -0.802
    },
    {
      "source": "Foundation for Defense of Democracies",
      "count": 1,
      "avg": 0.128
    },
    {
      "source": "ABC News & Headlines – Australian Broadcasting Corporation",
      "count": 1,
      "avg": -0.4215
    },
    {
      "source": "The Spectator",
      "count": 1,
      "avg": -0.8316
    },
    {
      "source": "Eurasia Review",
      "count": 1,
      "avg": -0.8385
    },
    {
      "source": "Il Sole 24 ORE",
      "count": 1,
      "avg": -0.9325
    },
    {
      "source": "KATU",
      "count": 1,
      "avg": -0.8481
    },
    {
      "source": "KHOU",
      "count": 1,
      "avg": -0.4939
    },
    {
      "source": "WesternSlopeNow.com",
      "count": 1,
      "avg": -0.6124
    },
    {
      "source": "Yahoo News Canada",
      "count": 1,
      "avg": -0.1027
    },
    {
      "source": "KABB",
      "count": 1,
      "avg": -0.8481
    },
    {
      "source": "KFXL",
      "count": 1,
      "avg": -0.8481
    },
    {
      "source": "Kyiv Post",
      "count": 1,
      "avg": 0.875
    },
    {
      "source": "KGAN",
      "count": 1,
      "avg": -0.8481
    },
    {
      "source": "CNA",
      "count": 1,
      "avg": -0.765
    },
    {
      "source": "شفق نيوز",
      "count": 1,
      "avg": -0.6124
    },
    {
      "source": "AnewZ",
      "count": 1,
      "avg": -0.886
    },
    {
      "source": "KTLA",
      "count": 1,
      "avg": -0.9042
    },
    {
      "source": "thecradle.co",
      "count": 1,
      "avg": -0.8316
    },
    {
      "source": "connectedtoindia.com",
      "count": 1,
      "avg": -0.9325
    },
    {
      "source": "The Express Tribune",
      "count": 1,
      "avg": -0.2023
    },
    {
      "source": "Scripps News",
      "count": 1,
      "avg": -0.8625
    },
    {
      "source": "FOX 29 Philadelphia",
      "count": 1,
      "avg": -0.9274
    },
    {
      "source": "Japan Wire by Kyodo News",
      "count": 1,
      "avg": 0.0
    },
    {
      "source": "FOX 9 Minneapolis-St. Paul",
      "count": 1,
      "avg": -0.4939
    },
    {
      "source": "AzerNews",
      "count": 1,
      "avg": -0.6597
    },
    {
      "source": "La Voce di New York",
      "count": 1,
      "avg": -0.9042
    },
    {
      "source": "Newser",
      "count": 1,
      "avg": -0.8625
    },
    {
      "source": "UN News",
      "count": 1,
      "avg": -0.0516
    },
    {
      "source": "Arab Center Washington DC",
      "count": 1,
      "avg": -0.6808
    },
    {
      "source": "IFCJ",
      "count": 1,
      "avg": -0.8481
    },
    {
      "source": "South China Morning Post",
      "count": 1,
      "avg": 0.0
    },
    {
      "source": "10News.com",
      "count": 1,
      "avg": -0.8625
    },
    {
      "source": "news8000.com",
      "count": 1,
      "avg": 0.1027
    },
    {
      "source": "Українські Новини",
      "count": 1,
      "avg": -0.2023
    },
    {
      "source": "Zeteo",
      "count": 1,
      "avg": 0.0
    },
    {
      "source": "Xinhua",
      "count": 1,
      "avg": -0.8316
    },
    {
      "source": "NewsCord",
      "count": 1,
      "avg": -0.7506
    },
    {
      "source": "chinadailyasia.com",
      "count": 1,
      "avg": 0.0
    },
    {
      "source": "Denver Gazette",
      "count": 1,
      "avg": -0.8481
    },
    {
      "source": "WOAI",
      "count": 1,
      "avg": -0.2023
    },
    {
      "source": "Tehran Times",
      "count": 1,
      "avg": -0.7351
    },
    {
      "source": "Firstpost",
      "count": 1,
      "avg": -0.6322
    },
    {
      "source": "WFLA",
      "count": 1,
      "avg": -0.2023
    },
    {
      "source": "FOX21 News Colorado",
      "count": 1,
      "avg": -0.2023
    },
    {
      "source": "WGN-TV",
      "count": 1,
      "avg": -0.7351
    },
    {
      "source": "WKU Public Radio",
      "count": 1,
      "avg": -0.6124
    },
    {
      "source": "Financial Times",
      "count": 1,
      "avg": -0.1531
    },
    {
      "source": "C-SPAN",
      "count": 1,
      "avg": -0.9153
    },
    {
      "source": "ABC7 Chicago",
      "count": 1,
      "avg": -0.5267
    },
    {
      "source": "조선일보",
      "count": 1,
      "avg": -0.8316
    }
  ],
  "top_entities": [
    {
      "name": "Iran",
      "type": "LOCATION",
      "count": 934,
      "avg": -0.4445
    },
    {
      "name": "Israel",
      "type": "LOCATION",
      "count": 911,
      "avg": -0.3725
    },
    {
      "name": "Donald Trump",
      "type": "PERSON",
      "count": 400,
      "avg": -0.3152
    },
    {
      "name": "Khamenei",
      "type": "PERSON",
      "count": 176,
      "avg": -0.5191
    },
    {
      "name": "Strait of Hormuz",
      "type": "LOCATION",
      "count": 123,
      "avg": -0.5068
    },
    {
      "name": "Tehran",
      "type": "LOCATION",
      "count": 112,
      "avg": -0.5565
    },
    {
      "name": "Benjamin Netanyahu",
      "type": "PERSON",
      "count": 104,
      "avg": -0.1326
    },
    {
      "name": "United States",
      "type": "LOCATION",
      "count": 73,
      "avg": -0.2806
    },
    {
      "name": "Jerusalem",
      "type": "LOCATION",
      "count": 67,
      "avg": -0.1946
    },
    {
      "name": "IDF",
      "type": "ORG",
      "count": 41,
      "avg": -0.5352
    },
    {
      "name": "IRGC",
      "type": "ORG",
      "count": 22,
      "avg": -0.6559
    },
    {
      "name": "Hezbollah",
      "type": "ORG",
      "count": 21,
      "avg": -0.3806
    },
    {
      "name": "Saudi Arabia",
      "type": "LOCATION",
      "count": 12,
      "avg": -0.4468
    },
    {
      "name": "Houthis",
      "type": "ORG",
      "count": 9,
      "avg": -0.4853
    },
    {
      "name": "Tel Aviv",
      "type": "LOCATION",
      "count": 7,
      "avg": -0.0038
    },
    {
      "name": "Masoud Pezeshkian",
      "type": "PERSON",
      "count": 3,
      "avg": -0.7432
    },
    {
      "name": "Natanz",
      "type": "LOCATION",
      "count": 1,
      "avg": -0.7506
    },
    {
      "name": "IAEA",
      "type": "ORG",
      "count": 1,
      "avg": -0.8316
    }
  ],
  "recent": [
    {
      "title": "Why the Iran-US ceasefire is falling apart",
      "source": "Al Jazeera",
      "url": "https://www.aljazeera.com/video/the-bottom-line/2026/7/12/why-the-iran-us-ceasefire-is-falling-apart?traffic_source=rss",
      "published": "2026-07-12T19:27:34+00:00",
      "compound": -0.4767,
      "label": "negative",
      "entities": [
        "Iran"
      ]
    },
    {
      "title": "Anti-migrant display set alight in Northern Ireland bonfire",
      "source": "Al Jazeera",
      "url": "https://www.aljazeera.com/video/newsfeed/2026/7/12/anti-migrant-display-set-alight-in-northern-ireland-bonfire?traffic_source=rss",
      "published": "2026-07-12T19:21:17+00:00",
      "compound": 0.3182,
      "label": "positive",
      "entities": []
    },
    {
      "title": "Friends turned foes: The split reshaping Senegal",
      "source": "Al Jazeera",
      "url": "https://www.aljazeera.com/video/talk-to-al-jazeera/2026/7/12/friends-turned-foes-the-split-reshaping-senegal?traffic_source=rss",
      "published": "2026-07-12T19:21:00+00:00",
      "compound": 0.0258,
      "label": "neutral",
      "entities": []
    },
    {
      "title": "IDF coordinates with US military, prepares for possible strikes as US, Iran fighting escalates",
      "source": "The Jerusalem Post",
      "url": "https://news.google.com/rss/articles/CBMiXEFVX3lxTE9lU2ZBUVFfMVlBcVpxX3ZjY0xRdVFjMDlvNW1pYmZoVzM0RkhwbWdpTVBPRDBOaWpfeWg1bk5GdzZ0NmZuSTBwb1U3RUlxMEw4dmVKUXZtMVl4eWJC?oc=5",
      "published": "2026-07-12T19:13:26+00:00",
      "compound": -0.8402,
      "label": "negative",
      "entities": [
        "IDF",
        "Iran",
        "Jerusalem"
      ]
    },
    {
      "title": "Graham pushed for Israel-Saudi normalization plan after Iran war",
      "source": "The Jerusalem Post",
      "url": "https://news.google.com/rss/articles/CBMiXEFVX3lxTE01MXE2Y3h4aXk2Y1QtTnJQLWlSbmZ0VGhNSTNLTnVQdFI0bXdjNWxZa3ZYRXlERTdWZTFURXVVQVF3MllkSmRvWE01WnZnZFc2OTBnellaaVlnNmFD?oc=5",
      "published": "2026-07-12T19:08:43+00:00",
      "compound": -0.8316,
      "label": "negative",
      "entities": [
        "Iran",
        "Israel",
        "Jerusalem",
        "Saudi Arabia"
      ]
    },
    {
      "title": "Some 30 Malian soldiers killed during Anefis retaking, says army chief",
      "source": "Al Jazeera",
      "url": "https://www.aljazeera.com/news/2026/7/12/some-30-malian-soldiers-killed-during-anefis-retaking-says-army-chief?traffic_source=rss",
      "published": "2026-07-12T19:01:40+00:00",
      "compound": -0.7906,
      "label": "negative",
      "entities": []
    },
    {
      "title": "South Africa says more than 53,000 foreigners deported in migration campaign",
      "source": "BBC",
      "url": "https://www.bbc.co.uk/news/articles/cvgj2prd4p8o?at_medium=RSS&at_campaign=rss",
      "published": "2026-07-12T18:57:17+00:00",
      "compound": -0.2263,
      "label": "negative",
      "entities": []
    },
    {
      "title": "Sen. Lindsey Graham on U.S.-Israel Strikes on Iran and War Powers Resolution",
      "source": "C-SPAN",
      "url": "https://news.google.com/rss/articles/CBMiuwFBVV95cUxNZmZ6R240RGlYWnR6dkx3dEx0MTRaYjhBRlUtd3dtTU4xNEQ0dTBIOWFBZmJXWjllMlNZYmRqNWtTWmlQWFhVTlRsOWRZeWNDc1E5bnRZNEUzUFg2OXFTNXBOUFYyNU5tR1dDVFFpemVPQ0RuQnpHeGZKVzBWTVRXa0FmaHlYVkg0dnZRYzRWcmdaT05JZG8xX1Z5ZFAtX1hEU3psWFBBUkxfVktqdWF1clFjSi01RFRfNU9N?oc=5",
      "published": "2026-07-12T18:54:50+00:00",
      "compound": -0.9153,
      "label": "negative",
      "entities": [
        "Iran",
        "Israel"
      ]
    },
    {
      "title": "Thousands gather to bid farewell to Qatar’s Father Emir Sheikh Hamad",
      "source": "Al Jazeera",
      "url": "https://www.aljazeera.com/video/newsfeed/2026/7/12/thousands-gather-to-bid-farewell-to-qatars-father-emir-sheikh-hamad?traffic_source=rss",
      "published": "2026-07-12T18:24:30+00:00",
      "compound": 0.0,
      "label": "neutral",
      "entities": []
    },
    {
      "title": "40 groups contest move to dilute environmental oversight of big projects",
      "source": "Times of Israel",
      "url": "https://www.timesofisrael.com/40-groups-contest-move-to-dilute-environmental-oversight-of-big-projects/",
      "published": "2026-07-12T18:11:56+00:00",
      "compound": -0.4215,
      "label": "negative",
      "entities": [
        "Israel"
      ]
    },
    {
      "title": "Rahm Emanuel warns Israel’s pariah status unsustainable amid US peace deal efforts",
      "source": "Crypto Briefing",
      "url": "https://news.google.com/rss/articles/CBMiowFBVV95cUxQUFhRb1F2bjNwWVlnLS1ZTF9aWnRHREplLXkxaWM5ZEhmZklQbTRJX2haYWtSMUNNaGhkczNUenNfWXNkbkJPLWFSLWpiTkJDMGtOclJLeEU0bFRnbGVuaEYxVnJlQmVJZElBMmxRZklrSVJMQ2FnX1plVUxDZzRWekRqTGpuUFowQTd5bmZCX1Ria004UXVmblJidUdzRWlkaWVr?oc=5",
      "published": "2026-07-12T18:08:50+00:00",
      "compound": 0.7351,
      "label": "positive",
      "entities": [
        "Israel"
      ]
    },
    {
      "title": "Concern for renewed war in Iran as US attacks military, civilian targets",
      "source": "Al Jazeera",
      "url": "https://news.google.com/rss/articles/CBMisgFBVV95cUxQcTZ3YWxEMV9tZGVTaEc5WGxLMGhfUHo0bzI5S0Z6VlN0QlFSMkF4MmtOMGo4d0VKc1dtUmdNT0pITksyTkVydTFLUGRQdW5EWklMMkRpNDBXMFRWc2xFNWY4MWg2Y002MUNNV2dUcGJmZ0pQUFY2UUlwN19nallMQldRMzNIZ2o3cXo0cmFfV0hUU3VuSmZkci1pMkVzVk1CSmlvdnh0S0RTTzZyX0Y4ck9R0gG3AUFVX3lxTE1uZnBLRVRJSjFkR1pQa0JuVlpTMzU5cjdYWE40RHNyc2lxT3VHUmVvMjMxSHFXcm9MaGprSENhdjBOaFRxMENRZFhqLUk4bnpBeUJCQ1FHd3ZWVHVNeTJ3OUlmZW1udUxmUTVKcDMxSjNZZFBjUm9DSmhCLTRpZ1lwaGoweUwzSXR4ODJOWmhudXVlMjdoSkpub2E5OGV1MzdrWEJiamZkVURoTktLZWotUVhKeTNmRQ?oc=5",
      "published": "2026-07-12T17:54:38+00:00",
      "compound": -0.9274,
      "label": "negative",
      "entities": [
        "Iran"
      ]
    },
    {
      "title": "Who will replace Trump ally Lindsey Graham in the US Senate?",
      "source": "Al Jazeera",
      "url": "https://www.aljazeera.com/news/2026/7/12/who-will-replace-trump-ally-lindsey-graham-in-the-us-senate?traffic_source=rss",
      "published": "2026-07-12T17:51:54+00:00",
      "compound": 0.0,
      "label": "neutral",
      "entities": [
        "Donald Trump"
      ]
    },
    {
      "title": "Israel's election will be held on October 27, coalition head says",
      "source": "Reuters",
      "url": "https://news.google.com/rss/articles/CBMitAFBVV95cUxQbVlfeEhKTEQwUVJDNzQ3eWVJM2JQd2JNMUZSV2pMVFRQUnp3YUNlN1RRQ2VmWVVITTZiUzJwZEJGbWVNUzR5Y0FPaHRZZU5YM0FpQ3Z0UWo1UGI5Tk9BNlNfNUhMMmRGckxhSHBDTzk5RWtsUTM5bGxfTjFkWEp3dF9Mb2RiT1kyNUZINksyTk9KQWt0Tk1qdjNjcjJqOURpUUxKQllTR2M3TC1wRzRLY3Z3N2o?oc=5",
      "published": "2026-07-12T17:50:55+00:00",
      "compound": 0.0,
      "label": "neutral",
      "entities": [
        "Israel"
      ]
    },
    {
      "title": "Concern for renewed war in Iran as US attacks military, civilian targets",
      "source": "Al Jazeera",
      "url": "https://www.aljazeera.com/news/2026/7/12/concern-for-renewed-war-in-iran-as-us-attacks-military-civilian-targets?traffic_source=rss",
      "published": "2026-07-12T17:50:27+00:00",
      "compound": -0.8225,
      "label": "negative",
      "entities": [
        "Iran",
        "Strait of Hormuz"
      ]
    },
    {
      "title": "Toronto police looking for suspects after deadly shooting at festival",
      "source": "NPR",
      "url": "https://www.npr.org/2026/07/12/g-s1-133229/toronto-shooting-salsa-festival",
      "published": "2026-07-12T17:22:29+00:00",
      "compound": 0.1779,
      "label": "positive",
      "entities": []
    },
    {
      "title": "IDF says it hit weapons site in Gaza, as 6 said killed in Strip, including girl",
      "source": "Times of Israel",
      "url": "https://www.timesofisrael.com/idf-says-it-hit-weapons-site-in-gaza-as-6-said-killed-in-strip-including-girl/",
      "published": "2026-07-12T17:17:04+00:00",
      "compound": -0.9801,
      "label": "negative",
      "entities": [
        "IDF",
        "Israel"
      ]
    },
    {
      "title": "Israel elections to be held on October 27: parliament",
      "source": "France 24",
      "url": "https://news.google.com/rss/articles/CBMioAFBVV95cUxPbVIyQVJKdzdJc3JZQlhOWUNpeTFaZlBrOTh1WFBaTGktam56SDBBOWhwOEp4NEluWmIyaFdqeFl3eUhFcGFFdzdfbnVpMlNrQUJocFc1ekdRMGFnMTduSWJMSUw2SHNRaWNhNlZWWFg3R05XeGMxR2JuYVFOWFNOLTFDUGZxOWtPV3dGSy1hdkNkc3hlTTJGc3puZC11UGkz?oc=5",
      "published": "2026-07-12T17:07:09+00:00",
      "compound": 0.0,
      "label": "neutral",
      "entities": [
        "Israel"
      ]
    },
    {
      "title": "The Guardian view on Trump and Tehran: everyone loses when the US and Iran overplay their hands | Editorial",
      "source": "The Guardian",
      "url": "https://www.theguardian.com/commentisfree/2026/jul/12/the-guardian-view-on-trump-and-tehran-everyone-loses-when-the-us-and-iran-overplay-their-hands",
      "published": "2026-07-12T17:02:12+00:00",
      "compound": -0.9873,
      "label": "negative",
      "entities": [
        "Donald Trump",
        "Iran",
        "Israel",
        "United States",
        "Tehran",
        "Strait of Hormuz"
      ]
    },
    {
      "title": "Lindsey Graham Championed Israel, Even as Wars Eroded American Support",
      "source": "The New York Times",
      "url": "https://news.google.com/rss/articles/CBMilwFBVV95cUxOc3dXeURnb1Rmd2FmTWszUWRNczlBMWJlSHJtV0FacGR3ZmtUQVVndldyNGNITjd2X2hNU3U2dGFsVzZsZHJsX3pHYUpDcEtMZGRmbG5LQzRuMFlCRlFYbTJCSUFmVlp6MGRWbVdQcjN1OVYzMTFUNkpXNTRkTnl0MVRSNU9qOC1hNHBYcUlkM0RsRm5WQXdB?oc=5",
      "published": "2026-07-12T17:00:50+00:00",
      "compound": 0.1531,
      "label": "positive",
      "entities": [
        "Israel"
      ]
    },
    {
      "title": "Qatar’s Father Emir Sheikh Hamad bin ⁠Khalifa Al Thani laid to rest in Doha",
      "source": "Al Jazeera",
      "url": "https://www.aljazeera.com/news/2026/7/12/funeral-prayers-held-for-qatars-father-emir-sheikh-hamad-in-doha?traffic_source=rss",
      "published": "2026-07-12T16:58:11+00:00",
      "compound": 0.0,
      "label": "neutral",
      "entities": []
    },
    {
      "title": "Transcript: Israeli Ambassador Michael Leiter on \"Face the Nation with Margaret Brennan,\" July 12, 2026",
      "source": "CBS News",
      "url": "https://news.google.com/rss/articles/CBMikwFBVV95cUxQOGF2Ulp4VmxMdjlVTTRPUk8wNXNKZjZlODlIMG1CaTh4UFMwdkllQUZ3cFYxN2otcnRNMnVUMGthUTM1NjVKYk1EaGlGVWx4WUxqLWNsQlJhT3N6dXJIVWhRQkFXY25QUWZBb2RzZ0FpQUxoMXo2V2FGVTQ5Z0xPOXliYUlZV1V5Wmt3Y0ZUQzVUemM?oc=5",
      "published": "2026-07-12T16:56:00+00:00",
      "compound": 0.0,
      "label": "neutral",
      "entities": [
        "Israel"
      ]
    },
    {
      "title": "UK Christians protest for Church of England to recognise genocide in Gaza",
      "source": "Al Jazeera",
      "url": "https://www.aljazeera.com/video/newsfeed/2026/7/12/uk-christians-protest-for-church-of-england-to-recognise-genocide-in-gaza?traffic_source=rss",
      "published": "2026-07-12T16:54:49+00:00",
      "compound": 0.1027,
      "label": "positive",
      "entities": []
    },
    {
      "title": "Election date finalized for October 27, with government set to complete full term",
      "source": "Times of Israel",
      "url": "https://www.timesofisrael.com/knesset-election-set-for-october-27-with-government-set-to-complete-full-term/",
      "published": "2026-07-12T16:53:56+00:00",
      "compound": 0.0,
      "label": "neutral",
      "entities": [
        "Benjamin Netanyahu",
        "Israel"
      ]
    },
    {
      "title": "Funeral prayers held for Qatar’s Father Emir Sheikh Hamad",
      "source": "Al Jazeera",
      "url": "https://www.aljazeera.com/video/newsfeed/2026/7/12/funeral-prayers-held-for-qatars-father-emir-sheikh-hamad?traffic_source=rss",
      "published": "2026-07-12T16:43:24+00:00",
      "compound": -0.6124,
      "label": "negative",
      "entities": []
    },
    {
      "title": "Iran war: US strategic success or diplomatic failure?",
      "source": "Al Jazeera",
      "url": "https://news.google.com/rss/articles/CBMiowFBVV95cUxON1RLajRNTko5d0dBT2VkRWw2ZENoQmwwSDJNRS1wczB5cnhJSEZBTFdDREJaTThVN1cyMUthUnhFU2dIa3Y5UzhLVmhlUEJFd1M4VWd2dlFsQXVMNk9Ya0c0YzN6ZHh1RFpGejg4V191ZEVrbENOZkktRldtWVk4SWt5R2hDck4wZDBxS1JxZ3piaHUxaHVPV2pRZlNvNVhHRlhZ0gGoAUFVX3lxTFBHdThneXZZb2xVNzNWMW5uMUc5WXZ6eUp6QU9saFVvdXJtRTRMUDd5bGhjOW5fd21iaWc3WHVkZ2VXVWF5S1RoRjNiM2pOcUJnUkk0OG9iZ0J6RTA2SzVBbWtZdUprMXZZOXAzY3VWREdfR2RVT284Rk1KZ2I5MjhRVWt5NS04dVFwRU1BOHc0bDNwaWpHY1oyMzdLNVdySHRiYzcwc2tVcg?oc=5",
      "published": "2026-07-12T16:38:57+00:00",
      "compound": -0.8105,
      "label": "negative",
      "entities": [
        "Iran"
      ]
    },
    {
      "title": "‘Sheikh Hamad will be fondly remembered across the Gulf’",
      "source": "Al Jazeera",
      "url": "https://www.aljazeera.com/video/newsfeed/2026/7/12/sheikh-hamad-will-be-fondly-remembered-across-the?traffic_source=rss",
      "published": "2026-07-12T16:38:34+00:00",
      "compound": 0.7003,
      "label": "positive",
      "entities": []
    },
    {
      "title": "Former Emir of Qatar Sheikh Hamad bin Khalifa Al Thani dies aged 74",
      "source": "BBC",
      "url": "https://www.bbc.co.uk/news/articles/cql1qdq14xro?at_medium=RSS&at_campaign=rss",
      "published": "2026-07-12T16:35:50+00:00",
      "compound": 0.0,
      "label": "neutral",
      "entities": []
    },
    {
      "title": "Iran war: US strategic success or diplomatic failure?",
      "source": "Al Jazeera",
      "url": "https://www.aljazeera.com/video/upfront/2026/7/12/iran-war-us-strategic-success-or-diplomatic-failure?traffic_source=rss",
      "published": "2026-07-12T16:34:17+00:00",
      "compound": -0.6486,
      "label": "negative",
      "entities": [
        "Iran",
        "Israel",
        "United States"
      ]
    },
    {
      "title": "FIFA World Cup 2026: Day 31",
      "source": "Al Jazeera",
      "url": "https://www.aljazeera.com/video/newsfeed/2026/7/12/fifa-world-cup-2026-day-31?traffic_source=rss",
      "published": "2026-07-12T16:30:57+00:00",
      "compound": 0.0258,
      "label": "neutral",
      "entities": []
    },
    {
      "title": "United States at 250: Seven tests of the American experiment",
      "source": "Al Jazeera",
      "url": "https://www.aljazeera.com/video/featured-documentaries/2026/7/12/united-states-at-250-seven-tests-of-the-american-experiment?traffic_source=rss",
      "published": "2026-07-12T16:30:00+00:00",
      "compound": 0.9349,
      "label": "positive",
      "entities": [
        "United States"
      ]
    },
    {
      "title": "Iranian media: Explosions heard near Bandar Abbas, around Qeshm Island",
      "source": "The Times of Israel",
      "url": "https://news.google.com/rss/articles/CBMitAFBVV95cUxNTmllbVQ2S3kydHNiRFp4V1pwREZreERQUmFtQXROMzNMV1hMU3ZicDJFek16aWVTZkVBaUZWYXhJUVlXUUZ4T2gxemJ5Ql94SjB1ekN6cjdHSzBqeHhRN3Vscmw1TDhTc09EYzM0aVprQ0pyWkVUWWN2UnZNNGthSTlDRnpXeHdhM04tYmdFVEJ5OWtmcHlVejJsS0hSNDZPT2c2UlFXWXlEdm1JT180YmxDTjI?oc=5",
      "published": "2026-07-12T16:12:18+00:00",
      "compound": 0.0,
      "label": "neutral",
      "entities": [
        "Iran",
        "Israel"
      ]
    },
    {
      "title": "Lindsey Graham, pro-Israel Republican senator, dies suddenly at 71",
      "source": "The Pittsburgh Jewish Chronicle",
      "url": "https://news.google.com/rss/articles/CBMiqwFBVV95cUxPekt6NHl1RWhKNkZXM05Jb3JUQWx0Um1tMTZwRDBuV0IyMWpaTEVqTUI1Y0QwQnQ5QzJiRG1UbTZJLXIzWW9ZTEd4WTlrNmRMT3dQbWY4VndEYjFHSXE4UHNWZWVmaXEyc1RtNmctam5UMldEVDNZeVlyWHhzVGRNN3laMDlCYi1PZnNHTVNjM2pSdmt1Qlo0WFFDOEhQYTREeE9OZ0EyYWpscjQ?oc=5",
      "published": "2026-07-12T16:07:19+00:00",
      "compound": 0.0,
      "label": "neutral",
      "entities": [
        "Israel"
      ]
    },
    {
      "title": "UK ambassador remembers former emir of Qatar as humble and humorous",
      "source": "Al Jazeera",
      "url": "https://www.aljazeera.com/video/newsfeed/2026/7/12/uk-ambassador-remembers-former-emir-of-qatar-as-humble-and-humorous?traffic_source=rss",
      "published": "2026-07-12T16:05:05+00:00",
      "compound": 0.3818,
      "label": "positive",
      "entities": []
    },
    {
      "title": "Lindsey Graham, US senator and staunch supporter of Israel, dies at 71",
      "source": "The Jerusalem Post",
      "url": "https://news.google.com/rss/articles/CBMiX0FVX3lxTE5tbjVCX3hYVUlsNnlYZ3dsWVpJcGE4T1l3MEdfVkVuUUN1bEgwZkNSUzk2eE5xVkJSTmhqYkRLUi1ZTXhTdVYzZ3A3eG1SaUZIV3lUYUZPZXlJN2hEdDlv?oc=5",
      "published": "2026-07-12T15:57:39+00:00",
      "compound": 0.4939,
      "label": "positive",
      "entities": [
        "Israel",
        "Jerusalem"
      ]
    },
    {
      "title": "Syrian parliament convenes for first time following al-Assad’s overthrow",
      "source": "Al Jazeera",
      "url": "https://www.aljazeera.com/news/2026/7/12/syrian-parliament-convenes-for-first-time-following-al-assads-overthrow?traffic_source=rss",
      "published": "2026-07-12T15:38:36+00:00",
      "compound": 0.4588,
      "label": "positive",
      "entities": []
    },
    {
      "title": "Meet the Cubans stuck in Mexico under Donald Trump’s deportation campaign",
      "source": "Al Jazeera",
      "url": "https://www.aljazeera.com/features/longform/2026/7/12/meet-the-cubans-stuck-in-mexico-under-donald-trumps-deportation-campaign?traffic_source=rss",
      "published": "2026-07-12T15:38:03+00:00",
      "compound": -0.2023,
      "label": "negative",
      "entities": [
        "Donald Trump"
      ]
    },
    {
      "title": "'This landscape is completely charred': Inside the village at epicentre of Spain's wildfires",
      "source": "BBC",
      "url": "https://www.bbc.co.uk/news/videos/cddl1yrldelo?at_medium=RSS&at_campaign=rss",
      "published": "2026-07-12T15:33:27+00:00",
      "compound": 0.0,
      "label": "neutral",
      "entities": []
    },
    {
      "title": "David Willey, esteemed BBC Vatican correspondent, dies aged 93",
      "source": "BBC",
      "url": "https://www.bbc.co.uk/news/articles/cn9403518jro?at_medium=RSS&at_campaign=rss",
      "published": "2026-07-12T15:22:52+00:00",
      "compound": 0.4404,
      "label": "positive",
      "entities": []
    },
    {
      "title": "Syria’s interim parliament meets for first time after Assad overthrow",
      "source": "Times of Israel",
      "url": "https://www.timesofisrael.com/syrias-interim-parliament-meets-for-first-time-after-assad-overthrow/",
      "published": "2026-07-12T15:16:45+00:00",
      "compound": -0.2023,
      "label": "negative",
      "entities": [
        "Israel"
      ]
    },
    {
      "title": "Israeli forces kill five Palestinians in latest attacks on Gaza",
      "source": "Al Jazeera",
      "url": "https://www.aljazeera.com/news/2026/7/12/israeli-forces-kill-five-palestinians-in-latest-attacks-on-gaza?traffic_source=rss",
      "published": "2026-07-12T15:16:44+00:00",
      "compound": -0.9432,
      "label": "negative",
      "entities": [
        "Israel"
      ]
    },
    {
      "title": "What made US Republican Senator Lindsey Graham a controversial figure",
      "source": "Al Jazeera",
      "url": "https://news.google.com/rss/articles/CBMirwFBVV95cUxNR3R2OEllWlRMdzRyRnB3YXlmWlMtdXFhUmRQQUN0T3diTjVCZGs3NVJjakxvTUtkM1lGQ2pIdlRJck95S2hjbkQ3SExndmtFU2E0dXRySERwMURWdDZYTkVsTHhzUXdDRUV5YnZnc1U0WEY3bnlVU21fZEFLem5nNl9MLXY4S0k4dGg4bVBqMHVuRUVqQ2hLaEhSQ01IRDhXWHN0cmpTckFDbmFNdEpv0gG0AUFVX3lxTE02RVBzdFozR0dXb0xRSjNrX3VqN1c0WVFhZEZsdlZmUDZ1cjRGaDRtWHVIU19IVEJteXhtS3ZScW1Eb1EteS1KZFZyckNDSENoVFZhbzJhZUtPajF4NTF6V0dVLWxwWnhlWEFRbmhNbXdIUGgyeXBObDJrclJmSk8wY3hoR0lJOHhESzl1VnIxeFFlWUNWMHlBczJxak9fUHhNTHdvaGd5TkhtUzRaZUJjWk5aXw?oc=5",
      "published": "2026-07-12T15:10:29+00:00",
      "compound": -0.3818,
      "label": "negative",
      "entities": []
    },
    {
      "title": "What made US Republican Senator Lindsey Graham a controversial figure",
      "source": "Al Jazeera",
      "url": "https://www.aljazeera.com/news/2026/7/12/what-made-us-republican-senator-lindsey-graham-a-controversial-figure?traffic_source=rss",
      "published": "2026-07-12T15:03:49+00:00",
      "compound": -0.1027,
      "label": "negative",
      "entities": []
    },
    {
      "title": "Beneath Beaufort’s strategic bulwark, a Hezbollah lair built to attack Israel is unearthed",
      "source": "Times of Israel",
      "url": "https://www.timesofisrael.com/beneath-beauforts-strategic-bulwark-a-hezbollah-lair-built-to-attack-israel-is-unearthed/",
      "published": "2026-07-12T15:00:52+00:00",
      "compound": -0.875,
      "label": "negative",
      "entities": [
        "IDF",
        "Hezbollah",
        "Iran",
        "Israel"
      ]
    },
    {
      "title": "Israel fires artillery into southern Lebanon amid fragile ceasefire",
      "source": "Crypto Briefing",
      "url": "https://news.google.com/rss/articles/CBMimwFBVV95cUxOZUc5MWE0bTBhc1FEdGN1MHNzaG9zN3BVd3NWaVpHNThvQkYtbG5LMDl4M0xDeDV5MmFRX3hCSzBYbjRGNzZSNUY2ZWtFNzFodDdNeXl0ejFlajFFMHJ0THlPWk5UNkZmZ3NnVEtiZy1YNThSamd4NjZlUWc1dnBjZlBxNlJ5Rm9wUF9xSmlWY0ROMHpkN05aZEtmYw?oc=5",
      "published": "2026-07-12T14:50:18+00:00",
      "compound": 0.0,
      "label": "neutral",
      "entities": [
        "Israel"
      ]
    },
    {
      "title": "FIFA, Infantino, to examine 64-team World Cup for 2030 tournament",
      "source": "Al Jazeera",
      "url": "https://www.aljazeera.com/sports/2026/7/12/fifa-infantino-to-examine-64-team-world-cup-for-2030-tournament?traffic_source=rss",
      "published": "2026-07-12T14:47:15+00:00",
      "compound": 0.0,
      "label": "neutral",
      "entities": []
    },
    {
      "title": "The architect of Qatari autonomy",
      "source": "Al Jazeera",
      "url": "https://www.aljazeera.com/opinions/2026/7/12/the-architect-of-qatari-autonomy?traffic_source=rss",
      "published": "2026-07-12T14:42:27+00:00",
      "compound": 0.4404,
      "label": "positive",
      "entities": []
    },
    {
      "title": "Israel-Iran War Ends with Politics-Religion Split",
      "source": "조선일보",
      "url": "https://news.google.com/rss/articles/CBMihwFBVV95cUxNNmRvUWhKUkp3dlBaa25RR0NJNUtWZk1GX0NZREt3d3h0N0NtNEdkVUJzcHRGdFoyS05wSlU5SmwzU1R4WGFLaV9OWjE4QVZnRldJQWttSE1EaV80R0ZmeDZaaEV3aGhXZEVPdDAtX2pMRkhaaXdVWmVkOHZUaHM5UjhxV1ZVbWc?oc=5",
      "published": "2026-07-12T14:41:21+00:00",
      "compound": -0.8316,
      "label": "negative",
      "entities": [
        "Iran",
        "Israel"
      ]
    },
    {
      "title": "Senator Lindsey Graham death: South Carolina senator draws tributes for his support of Ukraine, trans-Atlantic ties and Israel",
      "source": "ABC7 Chicago",
      "url": "https://news.google.com/rss/articles/CBMi1wFBVV95cUxPVzJnVGhoZllKdC1FVGdJNnlkcTF6d0VEeVJzVU1NZ0ZjVnhNR3BHSWZGSEhUSXJKYUtCeE51VzZ5elM3cmg2VzlSTGVUdVNwTEVmc042d3FjRkhRZVZQQk5wZm9KUWhWMTRwMWRHdG9RektqY0FZODhwbUs1a1B0RnJzcHI4RkpFdFdyak1yX09BR2tFa2dxaFdDZlZ0RUVScHhsVkg3UVBmMmZxUFpoNUVnR2JPY1Y0LVduaW93cVNJTmlXb0pJMkRKWXhVVjVFaGZxeXJxNNIB3AFBVV95cUxPN0hPX0d0a0Z6QmRzaUV4ZXkxTWduVVRYaEtHT3dMMWJyWnVnS1UxYlRhR0hsNi10SlRlbzB1Z3hnclF5TFVjQjdsc0p5MEVKdXJCTTM3c2pIWmJ0dlZVSVlrQ0FaNjg4VDVpNDE4Z09HZXZBX1FTakdjaFVfRDlqNTFxNmxqdW9yTEgzR2FNWEhHZEJ2YzJDZ2NWcm1MNVlFOENqeW1OQVQ5RG1BaFI2WHRVSVM2MDB3eEVUbUNDRHFHVnV5QWNUOXVVYloxQVZMZmNrZ0JwVG5Gck1j?oc=5",
      "published": "2026-07-12T14:28:12+00:00",
      "compound": -0.5267,
      "label": "negative",
      "entities": [
        "Israel"
      ]
    },
    {
      "title": "Driven by desperation: Yemenis resort to dangerous energy alternatives",
      "source": "Al Jazeera",
      "url": "https://www.aljazeera.com/news/2026/7/12/driven-by-desperation-yemenis-resort-to-dangerous-energy-alternatives?traffic_source=rss",
      "published": "2026-07-12T14:12:45+00:00",
      "compound": -0.5346,
      "label": "negative",
      "entities": []
    },
    {
      "title": "Lindsey Graham: A steadfast friend of Israel who never wavered",
      "source": "The Jerusalem Post",
      "url": "https://news.google.com/rss/articles/CBMiZEFVX3lxTE02TzBleVVZeWNpdTNZOEVZOEg3N2t4ejNXdHNKdFUwcnR6OGpiLUNUamFzUnpCNXFOV3F4ZzJUY0hqTDNia3FsaGdleW9POVBJcVlqR1d4WG4zQm9GeEt3WUpSUm8?oc=5",
      "published": "2026-07-12T14:01:08+00:00",
      "compound": 0.8555,
      "label": "positive",
      "entities": [
        "Israel",
        "Jerusalem"
      ]
    },
    {
      "title": "Marc Marquez dominates German MotoGP to close in on championship lead",
      "source": "Al Jazeera",
      "url": "https://www.aljazeera.com/sports/2026/7/12/marc-marquez-dominates-germany-motogp-to-close-in-on-championship-lead?traffic_source=rss",
      "published": "2026-07-12T13:45:32+00:00",
      "compound": 0.9485,
      "label": "positive",
      "entities": []
    },
    {
      "title": "Badly burned British couple rescued from ravine during Spain wildfires, reports say",
      "source": "BBC",
      "url": "https://www.bbc.co.uk/news/articles/cx2x7441762o?at_medium=RSS&at_campaign=rss",
      "published": "2026-07-12T13:35:01+00:00",
      "compound": -0.7964,
      "label": "negative",
      "entities": []
    },
    {
      "title": "Ukraine’s Zelenskyy announces cabinet reshuffle, replaces PM Svyrydenko",
      "source": "Al Jazeera",
      "url": "https://www.aljazeera.com/news/2026/7/12/ukraines-zelenskyy-announces-cabinet-reshuffle-replaces-pm-svyrydenko?traffic_source=rss",
      "published": "2026-07-12T13:28:53+00:00",
      "compound": 0.34,
      "label": "positive",
      "entities": []
    },
    {
      "title": "Live updates • All vessels can pass through Strait of Hormuz safely, U.S. military says",
      "source": "Haaretz",
      "url": "https://news.google.com/rss/articles/CBMimAJBVV95cUxQQTcwMlZubEhjOUxIWHgzUWNUa0FKUUgxZEptLVV6UXNzdkdUS0U0dlRMaFFXcmVNTXJYS2JNQTNTSDhRS21NeXFCZEl1a1hjME1aaW1hRkVwRmp0c3hpTW9Jb2tPUEhKSUVhUC16U2UxMXJwV2lmd1NLUnJPbTd1UlRNUWdlWTlmcTc5ZjFLdERHNUx0VlNidFNiOHQwaEhIQ3Nxc1NIRy1vTkxIWXRJcXozcXFvdGh5dWdoc2N2UlI3SlNrdDV4bVAwUndaWUtPZnhURUtEUlE0T2ZKWmZwRG4yYnBlNVZLUE5FbGFRVm43elU2Y01pRDIxOVlRbVdWS1B4Q19RQ25uVjE2QzMyNUZVbjlQNnlP?oc=5",
      "published": "2026-07-12T13:25:00+00:00",
      "compound": 0.7506,
      "label": "positive",
      "entities": [
        "Strait of Hormuz"
      ]
    },
    {
      "title": "Pape Thiaw fired as Senegal coach after disappointing FIFA World Cup",
      "source": "Al Jazeera",
      "url": "https://www.aljazeera.com/sports/2026/7/12/pape-thiaw-fired-as-senegal-coach-after-disappointing-fifa-world-cup?traffic_source=rss",
      "published": "2026-07-12T13:23:21+00:00",
      "compound": -0.7783,
      "label": "negative",
      "entities": []
    },
    {
      "title": "Former Emir Sheikh Hamad Bin Khalifa Al Thani’s legacy in Palestine",
      "source": "Al Jazeera",
      "url": "https://www.aljazeera.com/video/newsfeed/2026/7/12/former-emir-sheikh-hamad-bin-khalifa-al-thanis-legacy-in-palestine?traffic_source=rss",
      "published": "2026-07-12T13:21:17+00:00",
      "compound": 0.0,
      "label": "neutral",
      "entities": []
    },
    {
      "title": "Iran-US war latest: Strait of Hormuz closed indefinitely amid fresh strikes",
      "source": "The Independent",
      "url": "https://news.google.com/rss/articles/CBMixwFBVV95cUxPWDQtbVBHRGVsVFFCT2Y5VmNfNExJSmxzUjR6NURTUFhQbjIxTXU3U09GQk5hd3ZyMFcxY2pvMmVIbG5YM2d0U044VUZDa3djc2RZZ1ljODNNeERrbVpsTkFDYnZ6RGswWGR0NTJnaEp6eG9JWXNueTlqb1hSOC1DTUg4UTBuSFNiUjFDeExtSDhEMnVHaVZQejNkWEV0c3NEdkE5M2IxSnhyQWRva2VQLVJXa21QUGNCMzdUUWtLa0dKd3NCMF9r?oc=5",
      "published": "2026-07-12T13:19:14+00:00",
      "compound": -0.8481,
      "label": "negative",
      "entities": [
        "Iran",
        "Strait of Hormuz"
      ]
    },
    {
      "title": "Republican Lindsey Graham dies at 71: World leaders, US politicians react",
      "source": "Al Jazeera",
      "url": "https://www.aljazeera.com/news/2026/7/12/republican-lindsey-graham-dies-at-71-world-leaders-us-politicians-react?traffic_source=rss",
      "published": "2026-07-12T13:08:55+00:00",
      "compound": 0.0,
      "label": "neutral",
      "entities": [
        "Donald Trump"
      ]
    },
    {
      "title": "How Sheikh Hamad bin Khalifa Al Thani built Qatar’s soft power",
      "source": "Al Jazeera",
      "url": "https://www.aljazeera.com/news/2026/7/12/how-sheikh-hamad-bin-khalifa-al-thani-built-qatars-soft-power?traffic_source=rss",
      "published": "2026-07-12T13:08:39+00:00",
      "compound": 0.0,
      "label": "neutral",
      "entities": []
    }
  ]
}