{
  "id": "iran_israel",
  "name": "Irán–Israel/EE.UU.",
  "description": "Cobertura mediática del conflicto entre Irán, Israel y Estados Unidos",
  "updated": "2026-07-08T18:16:00+00:00",
  "total_articles": 1072,
  "overall_avg": -0.2822,
  "distribution": {
    "pos": 261,
    "neu": 170,
    "neg": 641
  },
  "sources": [
    "Al Jazeera",
    "Times of Israel",
    "BBC",
    "NPR",
    "The Times of Israel",
    "The Guardian",
    "The Jerusalem Post",
    "Reuters",
    "NBC News",
    "NDTV",
    "Ynetnews",
    "JNS",
    "The New York Times",
    "PBS",
    "Crypto Briefing",
    "Haaretz",
    "The Washington Post",
    "The Independent",
    "AP News",
    "The Times of India",
    "Fox News",
    "Israel National News",
    "Jewish Telegraphic Agency",
    "CNN",
    "ایران اینترنشنال",
    "JNS.org",
    "The Hill",
    "i24NEWS",
    "EA WorldView",
    "Middle East Eye",
    "New York Post",
    "Time Magazine",
    "CBC",
    "Washington Times",
    "Muslim Network TV",
    "Middle East Monitor",
    "Al-Monitor",
    "Anadolu Ajansı",
    "CBS News",
    "The Christian Science Monitor",
    "The New Arab",
    "Asharq Al-Awsat English",
    "www.israelhayom.com",
    "اسلام تايمز",
    "IranWire",
    "Al Arabiya English",
    "TheWire.in",
    "Egypt Independent",
    "Travel And Tour World",
    "The Indian Express",
    "Українські Національні Новини (УНН)",
    "The Forward",
    "The Federal",
    "thenationalnews.com",
    "middle-east-online.com",
    "Deccan Herald",
    "Radio Free Europe/Radio Liberty",
    "Truthout",
    "NewsNation",
    "+972 Magazine",
    "Euronews",
    "Encyclopedia Britannica",
    "France 24",
    "Council on Foreign Relations",
    "National Desk",
    "Mother Jones",
    "Boston Herald",
    "kmph.com",
    "vox.com",
    "Axios",
    "arabnews.jp",
    "TRT World",
    "WTAE",
    "CTech",
    "CSIS | Center for Strategic and International Studies",
    "The Economist",
    "NonStop Local Billings",
    "The New Yorker",
    "Arab News PK",
    "WDSU",
    "Kurdistan24",
    "Military.com",
    "Middle East Forum",
    "Foreign Policy",
    "The Washington Stand",
    "Begin-Sadat Center for Strategic Studies",
    "Türkiye Today",
    "Alma Research and Education Center",
    "PennLive.com",
    "6abc Philadelphia",
    "The Globe and Mail",
    "The Diplomatic Insight",
    "Plataforma Media",
    "The New Region",
    "bastillepost.com",
    "CairoScene",
    "WTVC",
    "WJAR",
    "National Herald",
    "Common Dreams",
    "The Business Standard",
    "Modern Ghana",
    "ABC7 Los Angeles",
    "Pajhwok Afghan News",
    "Salon.com",
    "CNBC",
    "KCRA",
    "Dawn",
    "Latest news from Azerbaijan",
    "KFOX",
    "L'Orient Today",
    "Informed Comment",
    "TV7 Israel News",
    "Infosecurity Magazine",
    "FOX4KC.com",
    "Politico",
    "Le Monde.fr",
    "The New York Sun",
    "PNI Atlantic News",
    "EFE - Agencia de noticias",
    "Jewish Insider",
    "Christianity Today",
    "The Israel Democracy Institute",
    "camera.org",
    "The Conversation",
    "The American Conservative",
    "U.S. News & World Report",
    "Drop Site News",
    "FOX40",
    "Forth.News",
    "Forbes",
    "ABC News - Breaking News, Latest News and Videos",
    "KSNV",
    "Democracy Now!",
    "Caspianpost.com",
    "GV Wire",
    "Межа. Новини України.",
    "تسنیم",
    "The Irish Times",
    "WION",
    "WDEF",
    "Yahoo News Australia",
    "The Salt Lake Tribune",
    "DW.com",
    "الحرة",
    "iranpress.com",
    "Investing.com Nigeria",
    "Quincy Institute for Responsible Statecraft",
    "Defense Priorities",
    "Baird Maritime",
    "Military Watch Magazine",
    "Benzinga",
    "The Media Line"
  ],
  "daily": [
    {
      "date": "2026-06-08",
      "count": 2,
      "avg": -0.4158,
      "pos": 0,
      "neu": 1,
      "neg": 1
    },
    {
      "date": "2026-06-14",
      "count": 3,
      "avg": -0.184,
      "pos": 1,
      "neu": 1,
      "neg": 1
    },
    {
      "date": "2026-06-15",
      "count": 3,
      "avg": -0.255,
      "pos": 1,
      "neu": 0,
      "neg": 2
    },
    {
      "date": "2026-06-16",
      "count": 4,
      "avg": -0.8085,
      "pos": 0,
      "neu": 0,
      "neg": 4
    },
    {
      "date": "2026-06-17",
      "count": 1,
      "avg": -0.802,
      "pos": 0,
      "neu": 0,
      "neg": 1
    },
    {
      "date": "2026-06-18",
      "count": 1,
      "avg": -0.2023,
      "pos": 0,
      "neu": 0,
      "neg": 1
    },
    {
      "date": "2026-06-19",
      "count": 7,
      "avg": -0.1603,
      "pos": 2,
      "neu": 1,
      "neg": 4
    },
    {
      "date": "2026-06-20",
      "count": 2,
      "avg": -0.3891,
      "pos": 0,
      "neu": 1,
      "neg": 1
    },
    {
      "date": "2026-06-21",
      "count": 2,
      "avg": -0.1077,
      "pos": 1,
      "neu": 0,
      "neg": 1
    },
    {
      "date": "2026-06-22",
      "count": 1,
      "avg": 0.802,
      "pos": 1,
      "neu": 0,
      "neg": 0
    },
    {
      "date": "2026-06-25",
      "count": 4,
      "avg": -0.1551,
      "pos": 1,
      "neu": 1,
      "neg": 2
    },
    {
      "date": "2026-06-26",
      "count": 3,
      "avg": -0.3428,
      "pos": 0,
      "neu": 1,
      "neg": 2
    },
    {
      "date": "2026-06-27",
      "count": 2,
      "avg": -0.5404,
      "pos": 0,
      "neu": 0,
      "neg": 2
    },
    {
      "date": "2026-06-28",
      "count": 7,
      "avg": -0.6537,
      "pos": 1,
      "neu": 0,
      "neg": 6
    },
    {
      "date": "2026-06-29",
      "count": 4,
      "avg": -0.4401,
      "pos": 1,
      "neu": 0,
      "neg": 3
    },
    {
      "date": "2026-06-30",
      "count": 1,
      "avg": 0.128,
      "pos": 1,
      "neu": 0,
      "neg": 0
    },
    {
      "date": "2026-07-01",
      "count": 2,
      "avg": -0.5957,
      "pos": 0,
      "neu": 0,
      "neg": 2
    },
    {
      "date": "2026-07-02",
      "count": 13,
      "avg": -0.4408,
      "pos": 2,
      "neu": 2,
      "neg": 9
    },
    {
      "date": "2026-07-03",
      "count": 39,
      "avg": -0.4568,
      "pos": 7,
      "neu": 2,
      "neg": 30
    },
    {
      "date": "2026-07-04",
      "count": 110,
      "avg": -0.2878,
      "pos": 26,
      "neu": 16,
      "neg": 68
    },
    {
      "date": "2026-07-05",
      "count": 182,
      "avg": -0.2261,
      "pos": 47,
      "neu": 29,
      "neg": 106
    },
    {
      "date": "2026-07-06",
      "count": 247,
      "avg": -0.2358,
      "pos": 68,
      "neu": 45,
      "neg": 134
    },
    {
      "date": "2026-07-07",
      "count": 217,
      "avg": -0.2544,
      "pos": 57,
      "neu": 39,
      "neg": 121
    },
    {
      "date": "2026-07-08",
      "count": 215,
      "avg": -0.3482,
      "pos": 44,
      "neu": 31,
      "neg": 140
    }
  ],
  "by_source": [
    {
      "source": "Al Jazeera",
      "count": 365,
      "avg": -0.2079
    },
    {
      "source": "Times of Israel",
      "count": 135,
      "avg": -0.2894
    },
    {
      "source": "BBC",
      "count": 121,
      "avg": -0.2237
    },
    {
      "source": "NPR",
      "count": 47,
      "avg": -0.2641
    },
    {
      "source": "The Times of Israel",
      "count": 46,
      "avg": -0.3508
    },
    {
      "source": "The Guardian",
      "count": 42,
      "avg": -0.5918
    },
    {
      "source": "The Jerusalem Post",
      "count": 26,
      "avg": -0.2554
    },
    {
      "source": "Reuters",
      "count": 16,
      "avg": -0.3695
    },
    {
      "source": "NBC News",
      "count": 8,
      "avg": -0.5808
    },
    {
      "source": "NDTV",
      "count": 8,
      "avg": -0.7452
    },
    {
      "source": "Ynetnews",
      "count": 8,
      "avg": -0.6693
    },
    {
      "source": "JNS",
      "count": 8,
      "avg": 0.0348
    },
    {
      "source": "The New York Times",
      "count": 7,
      "avg": -0.3707
    },
    {
      "source": "PBS",
      "count": 7,
      "avg": -0.3814
    },
    {
      "source": "Crypto Briefing",
      "count": 7,
      "avg": -0.5062
    },
    {
      "source": "Haaretz",
      "count": 6,
      "avg": -0.4317
    },
    {
      "source": "The Washington Post",
      "count": 5,
      "avg": -0.1336
    },
    {
      "source": "The Independent",
      "count": 5,
      "avg": -0.6376
    },
    {
      "source": "AP News",
      "count": 5,
      "avg": -0.5106
    },
    {
      "source": "The Times of India",
      "count": 5,
      "avg": -0.1504
    },
    {
      "source": "Fox News",
      "count": 5,
      "avg": -0.0276
    },
    {
      "source": "Israel National News",
      "count": 5,
      "avg": -0.2702
    },
    {
      "source": "Jewish Telegraphic Agency",
      "count": 5,
      "avg": 0.035
    },
    {
      "source": "CNN",
      "count": 4,
      "avg": -0.6182
    },
    {
      "source": "ایران اینترنشنال",
      "count": 4,
      "avg": -0.142
    },
    {
      "source": "JNS.org",
      "count": 4,
      "avg": 0.1963
    },
    {
      "source": "The Hill",
      "count": 3,
      "avg": -0.5093
    },
    {
      "source": "i24NEWS",
      "count": 3,
      "avg": -0.6791
    },
    {
      "source": "EA WorldView",
      "count": 3,
      "avg": -0.7804
    },
    {
      "source": "Middle East Eye",
      "count": 3,
      "avg": -0.5559
    },
    {
      "source": "New York Post",
      "count": 3,
      "avg": 0.231
    },
    {
      "source": "Time Magazine",
      "count": 3,
      "avg": 0.3293
    },
    {
      "source": "CBC",
      "count": 3,
      "avg": -0.0835
    },
    {
      "source": "Washington Times",
      "count": 3,
      "avg": 0.2441
    },
    {
      "source": "Muslim Network TV",
      "count": 3,
      "avg": -0.393
    },
    {
      "source": "Middle East Monitor",
      "count": 3,
      "avg": -0.7403
    },
    {
      "source": "Al-Monitor",
      "count": 3,
      "avg": 0.0636
    },
    {
      "source": "Anadolu Ajansı",
      "count": 2,
      "avg": -0.8679
    },
    {
      "source": "CBS News",
      "count": 2,
      "avg": -0.1771
    },
    {
      "source": "The Christian Science Monitor",
      "count": 2,
      "avg": -0.2069
    },
    {
      "source": "The New Arab",
      "count": 2,
      "avg": -0.2955
    },
    {
      "source": "Asharq Al-Awsat English",
      "count": 2,
      "avg": -0.247
    },
    {
      "source": "www.israelhayom.com",
      "count": 2,
      "avg": -0.8073
    },
    {
      "source": "اسلام تايمز",
      "count": 2,
      "avg": -0.9475
    },
    {
      "source": "IranWire",
      "count": 2,
      "avg": -0.3891
    },
    {
      "source": "Al Arabiya English",
      "count": 2,
      "avg": -0.3502
    },
    {
      "source": "TheWire.in",
      "count": 2,
      "avg": -0.8788
    },
    {
      "source": "Egypt Independent",
      "count": 2,
      "avg": -0.8584
    },
    {
      "source": "Travel And Tour World",
      "count": 2,
      "avg": -0.0455
    },
    {
      "source": "The Indian Express",
      "count": 2,
      "avg": -0.9508
    },
    {
      "source": "Українські Національні Новини (УНН)",
      "count": 2,
      "avg": -0.0407
    },
    {
      "source": "The Forward",
      "count": 2,
      "avg": 0.4884
    },
    {
      "source": "The Federal",
      "count": 2,
      "avg": -0.8926
    },
    {
      "source": "thenationalnews.com",
      "count": 2,
      "avg": -0.4662
    },
    {
      "source": "middle-east-online.com",
      "count": 2,
      "avg": -0.0826
    },
    {
      "source": "Deccan Herald",
      "count": 2,
      "avg": -0.4577
    },
    {
      "source": "Radio Free Europe/Radio Liberty",
      "count": 1,
      "avg": 0.7579
    },
    {
      "source": "Truthout",
      "count": 1,
      "avg": 0.7906
    },
    {
      "source": "NewsNation",
      "count": 1,
      "avg": -0.3818
    },
    {
      "source": "+972 Magazine",
      "count": 1,
      "avg": -0.8316
    },
    {
      "source": "Euronews",
      "count": 1,
      "avg": 0.0
    },
    {
      "source": "Encyclopedia Britannica",
      "count": 1,
      "avg": -0.7783
    },
    {
      "source": "France 24",
      "count": 1,
      "avg": -0.891
    },
    {
      "source": "Council on Foreign Relations",
      "count": 1,
      "avg": 0.0
    },
    {
      "source": "National Desk",
      "count": 1,
      "avg": -0.8481
    },
    {
      "source": "Mother Jones",
      "count": 1,
      "avg": 0.7003
    },
    {
      "source": "Boston Herald",
      "count": 1,
      "avg": -0.6124
    },
    {
      "source": "kmph.com",
      "count": 1,
      "avg": -0.8481
    },
    {
      "source": "vox.com",
      "count": 1,
      "avg": 0.0
    },
    {
      "source": "Axios",
      "count": 1,
      "avg": 0.802
    },
    {
      "source": "arabnews.jp",
      "count": 1,
      "avg": -0.9042
    },
    {
      "source": "TRT World",
      "count": 1,
      "avg": 0.1531
    },
    {
      "source": "WTAE",
      "count": 1,
      "avg": -0.7506
    },
    {
      "source": "CTech",
      "count": 1,
      "avg": -0.7906
    },
    {
      "source": "CSIS | Center for Strategic and International Studies",
      "count": 1,
      "avg": 0.0
    },
    {
      "source": "The Economist",
      "count": 1,
      "avg": 0.6072
    },
    {
      "source": "NonStop Local Billings",
      "count": 1,
      "avg": -0.4939
    },
    {
      "source": "The New Yorker",
      "count": 1,
      "avg": -0.8481
    },
    {
      "source": "Arab News PK",
      "count": 1,
      "avg": 0.7351
    },
    {
      "source": "WDSU",
      "count": 1,
      "avg": -0.7506
    },
    {
      "source": "Kurdistan24",
      "count": 1,
      "avg": -0.9001
    },
    {
      "source": "Military.com",
      "count": 1,
      "avg": 0.0
    },
    {
      "source": "Middle East Forum",
      "count": 1,
      "avg": 0.7741
    },
    {
      "source": "Foreign Policy",
      "count": 1,
      "avg": 0.0
    },
    {
      "source": "The Washington Stand",
      "count": 1,
      "avg": -0.7351
    },
    {
      "source": "Begin-Sadat Center for Strategic Studies",
      "count": 1,
      "avg": 0.0
    },
    {
      "source": "Türkiye Today",
      "count": 1,
      "avg": -0.8481
    },
    {
      "source": "Alma Research and Education Center",
      "count": 1,
      "avg": 0.0
    },
    {
      "source": "PennLive.com",
      "count": 1,
      "avg": 0.0
    },
    {
      "source": "6abc Philadelphia",
      "count": 1,
      "avg": -0.8957
    },
    {
      "source": "The Globe and Mail",
      "count": 1,
      "avg": -0.8402
    },
    {
      "source": "The Diplomatic Insight",
      "count": 1,
      "avg": -0.7003
    },
    {
      "source": "Plataforma Media",
      "count": 1,
      "avg": 0.0
    },
    {
      "source": "The New Region",
      "count": 1,
      "avg": -0.6369
    },
    {
      "source": "bastillepost.com",
      "count": 1,
      "avg": 0.0
    },
    {
      "source": "CairoScene",
      "count": 1,
      "avg": -0.8316
    },
    {
      "source": "WTVC",
      "count": 1,
      "avg": -0.8481
    },
    {
      "source": "WJAR",
      "count": 1,
      "avg": -0.8481
    },
    {
      "source": "National Herald",
      "count": 1,
      "avg": -0.8316
    },
    {
      "source": "Common Dreams",
      "count": 1,
      "avg": 0.836
    },
    {
      "source": "The Business Standard",
      "count": 1,
      "avg": 0.34
    },
    {
      "source": "Modern Ghana",
      "count": 1,
      "avg": -0.6124
    },
    {
      "source": "ABC7 Los Angeles",
      "count": 1,
      "avg": -0.8957
    },
    {
      "source": "Pajhwok Afghan News",
      "count": 1,
      "avg": -0.5267
    },
    {
      "source": "Salon.com",
      "count": 1,
      "avg": -0.7506
    },
    {
      "source": "CNBC",
      "count": 1,
      "avg": 0.296
    },
    {
      "source": "KCRA",
      "count": 1,
      "avg": -0.7506
    },
    {
      "source": "Dawn",
      "count": 1,
      "avg": -0.9153
    },
    {
      "source": "Latest news from Azerbaijan",
      "count": 1,
      "avg": -0.6369
    },
    {
      "source": "KFOX",
      "count": 1,
      "avg": -0.8481
    },
    {
      "source": "L'Orient Today",
      "count": 1,
      "avg": 0.6808
    },
    {
      "source": "Informed Comment",
      "count": 1,
      "avg": -0.8676
    },
    {
      "source": "TV7 Israel News",
      "count": 1,
      "avg": -0.9451
    },
    {
      "source": "Infosecurity Magazine",
      "count": 1,
      "avg": 0.0
    },
    {
      "source": "FOX4KC.com",
      "count": 1,
      "avg": -0.34
    },
    {
      "source": "Politico",
      "count": 1,
      "avg": 0.0
    },
    {
      "source": "Le Monde.fr",
      "count": 1,
      "avg": 0.0
    },
    {
      "source": "The New York Sun",
      "count": 1,
      "avg": -0.8126
    },
    {
      "source": "PNI Atlantic News",
      "count": 1,
      "avg": 0.0
    },
    {
      "source": "EFE - Agencia de noticias",
      "count": 1,
      "avg": -0.1531
    },
    {
      "source": "Jewish Insider",
      "count": 1,
      "avg": 0.7506
    },
    {
      "source": "Christianity Today",
      "count": 1,
      "avg": -0.9325
    },
    {
      "source": "The Israel Democracy Institute",
      "count": 1,
      "avg": 0.2023
    },
    {
      "source": "camera.org",
      "count": 1,
      "avg": -0.5267
    },
    {
      "source": "The Conversation",
      "count": 1,
      "avg": -0.7783
    },
    {
      "source": "The American Conservative",
      "count": 1,
      "avg": -0.0516
    },
    {
      "source": "U.S. News & World Report",
      "count": 1,
      "avg": 0.0
    },
    {
      "source": "Drop Site News",
      "count": 1,
      "avg": -0.9643
    },
    {
      "source": "FOX40",
      "count": 1,
      "avg": -0.34
    },
    {
      "source": "Forth.News",
      "count": 1,
      "avg": -0.6124
    },
    {
      "source": "Forbes",
      "count": 1,
      "avg": 0.0
    },
    {
      "source": "ABC News - Breaking News, Latest News and Videos",
      "count": 1,
      "avg": -0.9146
    },
    {
      "source": "KSNV",
      "count": 1,
      "avg": -0.4215
    },
    {
      "source": "Democracy Now!",
      "count": 1,
      "avg": 0.0
    },
    {
      "source": "Caspianpost.com",
      "count": 1,
      "avg": 0.7506
    },
    {
      "source": "GV Wire",
      "count": 1,
      "avg": -0.886
    },
    {
      "source": "Межа. Новини України.",
      "count": 1,
      "avg": -0.7003
    },
    {
      "source": "تسنیم",
      "count": 1,
      "avg": -0.8225
    },
    {
      "source": "The Irish Times",
      "count": 1,
      "avg": -0.9274
    },
    {
      "source": "WION",
      "count": 1,
      "avg": -0.7757
    },
    {
      "source": "WDEF",
      "count": 1,
      "avg": -0.7351
    },
    {
      "source": "Yahoo News Australia",
      "count": 1,
      "avg": -0.4215
    },
    {
      "source": "The Salt Lake Tribune",
      "count": 1,
      "avg": -0.25
    },
    {
      "source": "DW.com",
      "count": 1,
      "avg": 0.0
    },
    {
      "source": "الحرة",
      "count": 1,
      "avg": 0.0
    },
    {
      "source": "iranpress.com",
      "count": 1,
      "avg": -0.8225
    },
    {
      "source": "Investing.com Nigeria",
      "count": 1,
      "avg": 0.0
    },
    {
      "source": "Quincy Institute for Responsible Statecraft",
      "count": 1,
      "avg": 0.3182
    },
    {
      "source": "Defense Priorities",
      "count": 1,
      "avg": 0.128
    },
    {
      "source": "Baird Maritime",
      "count": 1,
      "avg": -0.4939
    },
    {
      "source": "Military Watch Magazine",
      "count": 1,
      "avg": 0.7003
    },
    {
      "source": "Benzinga",
      "count": 1,
      "avg": -0.6124
    },
    {
      "source": "The Media Line",
      "count": 1,
      "avg": -0.7783
    }
  ],
  "top_entities": [
    {
      "name": "Israel",
      "type": "LOCATION",
      "count": 465,
      "avg": -0.3603
    },
    {
      "name": "Iran",
      "type": "LOCATION",
      "count": 444,
      "avg": -0.4091
    },
    {
      "name": "Donald Trump",
      "type": "PERSON",
      "count": 166,
      "avg": -0.2576
    },
    {
      "name": "Khamenei",
      "type": "PERSON",
      "count": 139,
      "avg": -0.539
    },
    {
      "name": "Tehran",
      "type": "LOCATION",
      "count": 72,
      "avg": -0.4851
    },
    {
      "name": "Strait of Hormuz",
      "type": "LOCATION",
      "count": 64,
      "avg": -0.4762
    },
    {
      "name": "Benjamin Netanyahu",
      "type": "PERSON",
      "count": 62,
      "avg": -0.1061
    },
    {
      "name": "United States",
      "type": "LOCATION",
      "count": 38,
      "avg": -0.1902
    },
    {
      "name": "Jerusalem",
      "type": "LOCATION",
      "count": 35,
      "avg": -0.1891
    },
    {
      "name": "Hezbollah",
      "type": "ORG",
      "count": 14,
      "avg": -0.3413
    },
    {
      "name": "IDF",
      "type": "ORG",
      "count": 14,
      "avg": -0.6773
    },
    {
      "name": "Saudi Arabia",
      "type": "LOCATION",
      "count": 10,
      "avg": -0.4989
    },
    {
      "name": "Houthis",
      "type": "ORG",
      "count": 9,
      "avg": -0.4853
    },
    {
      "name": "IRGC",
      "type": "ORG",
      "count": 7,
      "avg": -0.6755
    },
    {
      "name": "Tel Aviv",
      "type": "LOCATION",
      "count": 3,
      "avg": -0.7088
    },
    {
      "name": "Natanz",
      "type": "LOCATION",
      "count": 1,
      "avg": -0.7506
    }
  ],
  "recent": [
    {
      "title": "Trump says ceasefire is 'over' after US and Iran trade strikes",
      "source": "BBC",
      "url": "https://www.bbc.co.uk/news/articles/clyw8w1g409o?at_medium=RSS&at_campaign=rss",
      "published": "2026-07-08T21:05:31+00:00",
      "compound": -0.296,
      "label": "negative",
      "entities": [
        "Donald Trump",
        "Iran"
      ]
    },
    {
      "title": "Middle East crisis live: Trump threatens US will hit Iran ‘hard again tonight’ after saying truce is over",
      "source": "The Guardian",
      "url": "https://www.theguardian.com/world/live/2026/jul/07/us-military-strikes-iran-war-latest-news-updates",
      "published": "2026-07-08T20:59:57+00:00",
      "compound": -0.9652,
      "label": "negative",
      "entities": [
        "Donald Trump",
        "Iran",
        "Israel",
        "Strait of Hormuz"
      ]
    },
    {
      "title": "France returns Syrian artefacts it’s held since civil war",
      "source": "Al Jazeera",
      "url": "https://www.aljazeera.com/video/newsfeed/2026/7/8/france-returns-syrian-artefacts-its-held-since-civil-war?traffic_source=rss",
      "published": "2026-07-08T20:55:38+00:00",
      "compound": -0.8316,
      "label": "negative",
      "entities": []
    },
    {
      "title": "Report: Hegseth cancels meeting with Netanyahu as Iran ceasefire shakes",
      "source": "KSNV",
      "url": "https://news.google.com/rss/articles/CBMi7AFBVV95cUxOd2JhTlRzR1NmeTJON2taSVVUa0V2ak5mWU9ETkYyeVo1TFlVbFdqVURwWGFsUThoSVNHSVlJeGVyZ3ROcjZDbmo0VkxEQTB2Vk5Ud0ZTNnhZZTVySTdZaEJVWlBwTDR6LWZYcTM1SWRwekFIcjM4N2JOYUJGZVdYODM3MU9ZN0JSZDdiWlRTbXdIb2F3N0pGRzUtcWtvQVFUVmticDVuWk15RjBPd2hUZ3NHR2RPV0dmU29SSFNQUVNzb1g4VVVZb1ZoX3ZKbUdqMlhNaGx5eUdmeUxCR1dzSWpLQkliT1ppMC1yWg?oc=5",
      "published": "2026-07-08T20:55:08+00:00",
      "compound": -0.4215,
      "label": "negative",
      "entities": [
        "Benjamin Netanyahu",
        "Iran"
      ]
    },
    {
      "title": "How Morocco can win the FIFA World Cup 2026 title",
      "source": "Al Jazeera",
      "url": "https://www.aljazeera.com/opinions/2026/7/8/how-morocco-can-win-the-fifa-world-cup-2026-title?traffic_source=rss",
      "published": "2026-07-08T20:42:44+00:00",
      "compound": 0.5994,
      "label": "positive",
      "entities": []
    },
    {
      "title": "Israel braces for possible renewal of fighting as US-Iran tensions mount – report",
      "source": "The Times of Israel",
      "url": "https://news.google.com/rss/articles/CBMiwwFBVV95cUxOQWR6WGU4YVctdW8xX2JQTW1iRjAwN3N5ME80ZmdKMVoyOHg0cUJGY1YtMGgwdm1sd1VXTlNrS0lCaXplQTA3SXNpLUx3ZVZIQXVOZ05iQkloNmtqaU1OaHpVMDRrRzdnSHpoUXJoc29xZzFoOHdBS3MtZllTVkJ0NC1tWk9FZm1zdGVsck1QYjI0Ym9VSE9BX1JiZjcwU0txR0JnRzJHbWFwSE9QOC1NWEJFNFByMDd4ZFY4NzRYcllfbnc?oc=5",
      "published": "2026-07-08T20:33:53+00:00",
      "compound": -0.8555,
      "label": "negative",
      "entities": [
        "Iran",
        "Israel"
      ]
    },
    {
      "title": "Live Updates: Latest from Israel, Iran, and Middle East",
      "source": "The Jerusalem Post",
      "url": "https://news.google.com/rss/articles/CBMif0FVX3lxTE5STkZIWE5mTVJtX1BFbGtnaUZoN0Uwc2hRVXVMZlc0MlpaSktvS1JSbnVPNmV3R0hjbU1FeEx5cDhwLVh4QVhacUtuS2MtVTdJS2dSd0o5OGxFVHdUUmtvaDUxU1lRd3lWSnFkdGxYSVFqaTczVTJ1ZW5wOEhTNm8?oc=5",
      "published": "2026-07-08T20:33:34+00:00",
      "compound": 0.0,
      "label": "neutral",
      "entities": [
        "Iran",
        "Israel",
        "Jerusalem"
      ]
    },
    {
      "title": "Nigeria's president demands to know how fake agency was allegedly set up in his office",
      "source": "BBC",
      "url": "https://www.bbc.co.uk/news/articles/c621xrrp6jeo?at_medium=RSS&at_campaign=rss",
      "published": "2026-07-08T20:31:47+00:00",
      "compound": -0.1027,
      "label": "negative",
      "entities": []
    },
    {
      "title": "Called to serve, determined to succeed: The reservists redefining resilience at Reichman University - Sponsored Content",
      "source": "Times of Israel",
      "url": "https://www.timesofisrael.com/spotlight/called-to-serve-determined-to-succeed-the-reservists-redefining-resilience-at-reichman-university/",
      "published": "2026-07-08T20:30:05+00:00",
      "compound": 0.9153,
      "label": "positive",
      "entities": [
        "Israel"
      ]
    },
    {
      "title": "New U.S. passports with Trump's image are available. Here's how to get (or avoid) one",
      "source": "NPR",
      "url": "https://www.npr.org/2026/07/08/g-s1-132497/passports-trump-image",
      "published": "2026-07-08T20:27:33+00:00",
      "compound": -0.296,
      "label": "negative",
      "entities": [
        "Donald Trump",
        "United States"
      ]
    },
    {
      "title": "Trump at NATO: 'I'm number one on Iran's kill list'",
      "source": "Israel National News",
      "url": "https://news.google.com/rss/articles/CBMiWkFVX3lxTE1aVlZVeGV1LWF3MnBqb3NIaDdrWTlrZ002VUduSHFpMUdLVUJFR1ZvOGpxYi1LNmtTaUJwczJMN2lVX0JZX2FZVTJGWkxJLTBMTnZmSWFmb0Y4UQ?oc=5",
      "published": "2026-07-08T20:26:00+00:00",
      "compound": -0.8689,
      "label": "negative",
      "entities": [
        "Donald Trump",
        "Iran",
        "Israel"
      ]
    },
    {
      "title": "NATO pledges 70 billion euros for Ukraine as Trump praises peace ‘progress’",
      "source": "Al Jazeera",
      "url": "https://www.aljazeera.com/news/2026/7/8/nato-pledges-70-billion-euros-for-ukraine-as-trump-praises-peace-progress?traffic_source=rss",
      "published": "2026-07-08T20:24:45+00:00",
      "compound": 0.8779,
      "label": "positive",
      "entities": [
        "Donald Trump"
      ]
    },
    {
      "title": "European regulators loosen restrictions on flights to Israel",
      "source": "Jewish Telegraphic Agency",
      "url": "https://news.google.com/rss/articles/CBMinwFBVV95cUxOeWVXVnh1STM0a1NKVWM2aG5yVkZnTUp2aWszQl93VXNUOWZncEN0TU9rWHgtOUlwTVpURWdTTGhSSXlzRmg4LU1VejFHQ1BSSW5iN0x0T1FLWTJRTGtyaFd2R1BJcFdyUmM4VEJwcFhPQWtvcVZoNjRJN21tQm9KZTNpRGtmNkd1YWlJaDJ2YmFzNXNJS0daUzIxMm1wV1U?oc=5",
      "published": "2026-07-08T20:23:46+00:00",
      "compound": 0.0,
      "label": "neutral",
      "entities": [
        "Israel"
      ]
    },
    {
      "title": "Ukraine to get licence to produce Patriot missiles, Trump says",
      "source": "BBC",
      "url": "https://www.bbc.co.uk/news/articles/ce8klree690o?at_medium=RSS&at_campaign=rss",
      "published": "2026-07-08T20:18:14+00:00",
      "compound": 0.5256,
      "label": "positive",
      "entities": [
        "Donald Trump"
      ]
    },
    {
      "title": "Poll: Israelis lose confidence in Trump after Iran deal",
      "source": "Israel National News",
      "url": "https://news.google.com/rss/articles/CBMiWkFVX3lxTE1IT1NsSlI0MHpmRzZzbGFfUVFObnNtYTZVaWZTbGY5UkFPQWk5ZFlqcHZwVVlyTHRHcGJKSHkzZXVBZVhXem1CWmFBSmVLN2hEUzc0b1lmcDVOZw?oc=5",
      "published": "2026-07-08T20:18:00+00:00",
      "compound": 0.296,
      "label": "positive",
      "entities": [
        "Donald Trump",
        "Iran",
        "Israel"
      ]
    },
    {
      "title": "'Exercise Restraint, Return To Diplomacy': India On Fresh Middle-East Tensions",
      "source": "NDTV",
      "url": "https://news.google.com/rss/articles/CBMizwFBVV95cUxPX0pma1FDN0VkaS1rbXZ3WXh5dlF1TVRKZ0EwcWJRSjhpR1pVd0NjanBDeUhpcGhod0NfXzZ0dkFfeHBwdXAwRWlLSFVOWGlvWjN0NXhDdGE4QWFOd2tIcG9zaHZ4TGlLWU1sU1NVZFh4LThBdnNnNG50OF91VTZDLVVjZFJqbDhJZE44elFfbGRrNE56WFlDTU5GQWZMcG1HSEZOMzQxWEFGOGVneFI5eHh1bk40SUVuMlo5aXFqaUFxNzNWcjM4aDFvOUZsUk3SAdcBQVVfeXFMT3pCWlItVVc3OHhXRWltV2lBTHhPTy0wYlBZM2JmZG1aeEZHbE1HRDRfcWJzeURqUWhpcnAyZVRUYjZPd3F2YUJNcjVtMTl3akt2WnZMMWFncXZ3ZzNMWEhrYXpoRWRCUVZDSEdmaTIwa1kxUHRuMjkxb3hmMHJ1UDlWNXl5bTFyWFVMV2ZOSmxaeXNnYXBMR2pwclJMUDFhdllSaDNzNklFMzBIakZsSHE4clJMZ1NxVjl4ZFMzTnVqRmJhQld1MW1LMVIxTEVTRGNuT0dtNG8?oc=5",
      "published": "2026-07-08T20:17:54+00:00",
      "compound": -0.2023,
      "label": "negative",
      "entities": []
    },
    {
      "title": "Live updates • Nine killed by Israeli strikes in Gaza Strip on Wednesday, health officials say",
      "source": "Haaretz",
      "url": "https://news.google.com/rss/articles/CBMimgJBVV95cUxOQUxuaG1WLVJaa1ktRnNPTFphc2kwRFFQT2F5cDRldzFqYnFIZ2RFV09OTGlmZE5SUy1maThINXVEam5aczVreTF1dGhKR2ZlbUVsenZiZ0dBNHJ5Y1N6NEp4NU01RGZTMjA0RkpLMkJsckhxY2N5d3lVY0cwRHdraU93SlhKY0FyUVVxQlpxNTFGMWlOb0xpZV9qYklUZzZqN1ZRM0V3QzVMMWdBOHdEcE9Fd3BFZkU2QVMwZ2dlNmtoWmNtaFNROUw4aHRhMXd2N3V6ZHVNNGJ4clQzNmMwWXdLc3pLUnh0VTlWRHNjTVZxRDBKMFVJLURuV24tM0paamJkd0JRSkZ2aEpwSmRuZGRDaWk1bnpwQWc?oc=5",
      "published": "2026-07-08T20:12:00+00:00",
      "compound": -0.9325,
      "label": "negative",
      "entities": [
        "Israel"
      ]
    },
    {
      "title": "Trump says ceasefire is 'over' after US and Iran trade strikes",
      "source": "BBC",
      "url": "https://news.google.com/rss/articles/CBMiWkFVX3lxTE5FVXdyTnl5aUpzSmVjVzl6ZzB4bGxFSmhxaEhGQ2xCdl84M0hZYkxqdGFUcmlUTV93TUJFejllckdnVFNUVFREcnlIX3duNGgwN0VUVHE1RlhKQQ?oc=5",
      "published": "2026-07-08T20:01:49+00:00",
      "compound": -0.6124,
      "label": "negative",
      "entities": [
        "Donald Trump",
        "Iran"
      ]
    },
    {
      "title": "Iran war live: Trump says MoU to end Iran war is ‘over’",
      "source": "Al Jazeera",
      "url": "https://news.google.com/rss/articles/CBMitwFBVV95cUxQd2Z4M3hOV2ZEdjBGdnhaLWFnS3JVU3g2S3hDbnE4NnU4Vzkzb081elViZ3VBaEtxZlNmdktwb2c0eW96dldZT1pvSmR3N1RYWFE4UFpqZFIzSlNLMy0xM2dTTVllRmxGUFRMQ0xsbWZNX09vcmJJeHV0ZVlPNHg0NnBfS0JzQ01fa0dncGJKckd5S1dBSU5vXzFoUE5ZdUQxVUhDbG5KaDVaazhydjhERjU5SS1zSVXSAbwBQVVfeXFMUFRKTEtCaGQ3ZlV5MlZoQ05CeThIeDd0Sng5OTZ4aG1JNm8wTmhrbDZFZFJMclI0MUZpWS1jY0hSUHhFN2g2S2RfUndlaFVtMUk4TVl0RWZ1MWZFS3VOQUkwakpFZ3lLYTBGOXFQdkhOc0RDWHloVG1aQW8yQS1pN1NldjlUOXgweDY0aGtOMkxSQ25CdE9tdDN0VW9pOExVOHJvdFJEcjB0empwYTJYbE1PclZaRnNlNnBGSTA?oc=5",
      "published": "2026-07-08T19:54:59+00:00",
      "compound": -0.9485,
      "label": "negative",
      "entities": [
        "Donald Trump",
        "Iran"
      ]
    },
    {
      "title": "The Strait of Hormuz is now at the centre of Iranian and US calculus",
      "source": "Al Jazeera",
      "url": "https://news.google.com/rss/articles/CBMisgFBVV95cUxOdHlaX0VSVjZpYkpVUDAwaVNUeUc1bFAxS1BOTlBMaTBQbTdCWEcwanRZZXJYYlhGcEFfUTNKTHRUdWtQZGJwY20yZ2pydl90UExuaHg1MDdVQlVCMU1LTjZkSFBWZGRFS3VzVUpjZ1czVWZCcUhqdWgyazZMQjFlUUtHV0YzRDRybWZWLWhLZFpfNFZiM185ZDQ4ZE1acjRHUkhTRTl3SVVKcmhmQ2tkRTl30gG3AUFVX3lxTE9FcFhsVF80NEpMQU9yZVN3bm5aSm5aZVJSM3IySXNCcF93WHViWDh6UWJKZUFWdFNoV0RPVkptMUtXLVJuVnI4Rjd5TVV1bUNIN3NDMXBDdkNaS1dhdVN1anhFN29JZGcyWS1pVVRzUlB4N1haaHpUMFRrWktoVHZNQ1o4bmt3eEFPdGRQRnNZNEF1NFYzdmFKWW4wX1pRUng0N09uNjFjQjBNc1NLSTB6eWFCR2Z3VQ?oc=5",
      "published": "2026-07-08T19:52:27+00:00",
      "compound": 0.0,
      "label": "neutral",
      "entities": [
        "Iran",
        "Strait of Hormuz"
      ]
    },
    {
      "title": "The Strait of Hormuz is now at the centre of Iranian and US calculus",
      "source": "Al Jazeera",
      "url": "https://www.aljazeera.com/opinions/2026/7/8/the-strait-of-hormuz-is-now-at-the-centre-of-iranian-and-us-calculus?traffic_source=rss",
      "published": "2026-07-08T19:48:31+00:00",
      "compound": 0.0,
      "label": "neutral",
      "entities": [
        "Iran",
        "Strait of Hormuz"
      ]
    },
    {
      "title": "US charges Indian crime leader in Sikh activist’s assassination",
      "source": "Al Jazeera",
      "url": "https://www.aljazeera.com/news/2026/7/8/us-charges-indian-crime-leader-in-sikh-activists-assassination?traffic_source=rss",
      "published": "2026-07-08T19:44:39+00:00",
      "compound": -0.9643,
      "label": "negative",
      "entities": []
    },
    {
      "title": "Egypt criticises ‘influential refereeing’ in Argentina World Cup match",
      "source": "Al Jazeera",
      "url": "https://www.aljazeera.com/sports/2026/7/8/egypt-criticises-influential-refereeing-in-argentina-world-cup-match?traffic_source=rss",
      "published": "2026-07-08T19:41:58+00:00",
      "compound": -0.5423,
      "label": "negative",
      "entities": []
    },
    {
      "title": "EU aviation agency urges avoiding Iran, Iraq, Lebanon airspaces until August 31",
      "source": "Times of Israel",
      "url": "https://www.timesofisrael.com/eu-aviation-agency-urges-avoiding-iran-iraq-lebanon-airspaces-until-august-31/",
      "published": "2026-07-08T19:31:43+00:00",
      "compound": -0.836,
      "label": "negative",
      "entities": [
        "Iran",
        "Israel"
      ]
    },
    {
      "title": "Israel prepares for possibility of renewed full-scale war following US attacks on Iran",
      "source": "The Irish Times",
      "url": "https://news.google.com/rss/articles/CBMi2wFBVV95cUxQWmlpdlZHVVl1cGRkanRvZlJqWEtZQUtISHlfcEFWYnN1bGpNeFRvMEJRdVE1V0pJc3puVXpFTUdoMUMtM3NuTHRaU1ktNW80SzJxZkVJb2dkUDJZLUpEMkdsQXhzX2d2QW4zbFdJX0F2dmE1cHU1Mk80X09wWW13czFwb3FKeGRMY3dnOVJsMTd4eXlEd2dpSnZ4Umh6bFd0alZWSDZuZDMycWM1M1UzSXdfWFM2RThaUF8xWks4a0ZrdElFVGtMV2hMQjBKR3ZkRV9vLTRFUmFHU0E?oc=5",
      "published": "2026-07-08T19:30:07+00:00",
      "compound": -0.9274,
      "label": "negative",
      "entities": [
        "Iran",
        "Israel"
      ]
    },
    {
      "title": "Trump says ceasefire ‘over’, re-ups threats after US and Iran trade attacks",
      "source": "Al Jazeera",
      "url": "https://news.google.com/rss/articles/CBMimAFBVV95cUxOWFVjdnhLM1JwSlQtRXRlblRpWlRqaU5Qbk5DenNSOTBabkVfTDFMbE5Hb3NhTnJLT21lTjhSNjF4TXZCYlpHakwxYzZfS3c2UktXclM4RDlHZXdmdXFyd1RkX0R5MW1ZM3pZaTd2WkJ0UGJWUWdJZ0NHck9Hd0ZFWWtBdlBUMFdDeHhfb0s5MXA3MEFDdGJOTtIBngFBVV95cUxNRDBFVnkza3pRTGJiZmdMTjBaU0hWWFQ0T25oc0FhbXhkdW5LZG5icUR6WG1QVEFfaDRLMWFuSUEyU3gyZmdnQV90dEc3TWRPLWhnbjc1SzZqWVltdDRfUzAwVVJBYk9BcXRfN1g1MnZnSXNvNWtqSkt2UXk1N01Kd21IS1RKQXdxZWhFUV9IRTFaUjZOejVCZlo1NlRKZw?oc=5",
      "published": "2026-07-08T19:30:00+00:00",
      "compound": -0.886,
      "label": "negative",
      "entities": [
        "Donald Trump",
        "Iran"
      ]
    },
    {
      "title": "Trump says US to again ‘hit Iran hard’",
      "source": "JNS",
      "url": "https://news.google.com/rss/articles/CBMiiAFBVV95cUxOWmlRQVQ4MUM4SU1LU01mOXBuOHhNWFFDQTZXS1BYRUUwTVkzMW00SXV2RDlYeEJpaXBuTUdGeWtkSlNoZmEyWFNGQVFxTzdCREV5cEVCdzFGV21aczJfQWxuZjcwa2J4Y2xXZGliVTlVMGVxVjB3X0Uyd0RWVU1SVFpNc0NRZFY5?oc=5",
      "published": "2026-07-08T19:18:45+00:00",
      "compound": 0.0,
      "label": "neutral",
      "entities": [
        "Donald Trump",
        "Iran"
      ]
    },
    {
      "title": "The IOC clears the way for Russian athletes to return to Olympic competition",
      "source": "NPR",
      "url": "https://www.npr.org/2026/07/08/g-s1-132480/russia-olympics-ioc-decision",
      "published": "2026-07-08T19:17:37+00:00",
      "compound": -0.5574,
      "label": "negative",
      "entities": []
    },
    {
      "title": "Far-right leader Le Pen starts campaign, faces mixed reactions in France",
      "source": "Al Jazeera",
      "url": "https://www.aljazeera.com/news/2026/7/8/far-right-leader-le-pen-starts-campaign-faces-mixed-reactions-in-france?traffic_source=rss",
      "published": "2026-07-08T19:17:12+00:00",
      "compound": 0.0,
      "label": "neutral",
      "entities": []
    },
    {
      "title": "Trump warns Iran that US is preparing for more strikes after saying ceasefire is over",
      "source": "AP News",
      "url": "https://news.google.com/rss/articles/CBMimgFBVV95cUxQTXRXN1ZOY3dWb0Y3bFliM0t6QVRjQkxGNmNRRkVPM29YazVXaXVpaFo3N2h2MHdBLUlTMWNROTJuTUJQNFhaR3BwTzV5b0NDYk1WOG5NMXRHLWhuNHF1NXJqOFM0Vzg2TWo2bXRCUS11WmFEeU45UURDV0dqX0szLWxfbkptQXFxQVJXM0hjY2lkS1VJdkljZWFR?oc=5",
      "published": "2026-07-08T19:16:00+00:00",
      "compound": -0.7496,
      "label": "negative",
      "entities": [
        "Donald Trump",
        "Iran"
      ]
    },
    {
      "title": "Germany urges US-Iran negotiations, offers to minesweep Hormuz",
      "source": "Al Jazeera",
      "url": "https://news.google.com/rss/articles/CBMisAFBVV95cUxORUZVV1pOSk9yLXdjVnFMWVAzbGJKMWh1ZlhlbFJ6V2tiYmstbTlSTzlsX005ZHVXREotNzFQdUhMM3hvOEhrbWR3QTBOeHRiSFQ5ZGdIM1k0YTVFNWpud0Y3U254c3MtUUQtQlUzb294cnZlbDh3OGJVWll2bUNiYW8wUUN6Y2x2NUVQUURNbG8tNVpQRWJ3OEM3bFRFOVN2b3ZhZXZpM2NnNjhaVDRNZtIBtgFBVV95cUxOSVozVFdrNkxwMzhveVktc0k3NS11dlBKTG9mWE9vM210dWctMnpuTzlWM2V3NWlHc0E4akdOalFDRzBXLVFoNEFKUDR4V09FUDhVREFHYzExNGFyODdXUV92a29INXVKempYNnpXbmU0c2F6N3czWG1ENjhURlotZW5aQlVHWXdGOUZZNUU2WlFzeEZMNmxqM282OWZVOTRfNzN3dkRFRHNLTDBuWkdMSEhocEh6Zw?oc=5",
      "published": "2026-07-08T19:13:07+00:00",
      "compound": 0.0,
      "label": "neutral",
      "entities": [
        "Iran",
        "Strait of Hormuz"
      ]
    },
    {
      "title": "Arizona toddler found alive in hospital morgue after declared dead from drowning",
      "source": "BBC",
      "url": "https://www.bbc.co.uk/news/articles/cvg5x0vvrmro?at_medium=RSS&at_campaign=rss",
      "published": "2026-07-08T19:12:50+00:00",
      "compound": 0.4939,
      "label": "positive",
      "entities": []
    },
    {
      "title": "Israel raises alert level to maximum amid anticipated resumption of war with Iran",
      "source": "Crypto Briefing",
      "url": "https://news.google.com/rss/articles/CBMipwFBVV95cUxOYTd6Y1hzSzZNZzRVSW9rZnlOVV9TVDRWRTF4M1pjUV9FMnBHQkYwM1BaanhPSnBOLTNlaEJvSlZ6OGJ0YktodktEUktFSXVHeWwycTF2SWRnMDFfNWZvay1xT0RJaU16U3diY2lJLWFrWXJVanlLMmZoOEpvVWRIS1pncFVwUkhYOFdaeVRLR2Q1SF9QNVJuN2xTbmlPRFh2bnFld0hMOA?oc=5",
      "published": "2026-07-08T19:11:54+00:00",
      "compound": -0.6597,
      "label": "negative",
      "entities": [
        "Iran",
        "Israel"
      ]
    },
    {
      "title": "Pakistan military says 42 killed in fighter attacks in Balochistan",
      "source": "Al Jazeera",
      "url": "https://www.aljazeera.com/news/2026/7/8/pakistan-military-says-42-killed-in-fighter-attacks-in-balochistan?traffic_source=rss",
      "published": "2026-07-08T19:07:45+00:00",
      "compound": -0.8957,
      "label": "negative",
      "entities": []
    },
    {
      "title": "Oil for unity: What is the US mediation plan in Libya?",
      "source": "Al Jazeera",
      "url": "https://www.aljazeera.com/news/2026/7/8/oil-for-unity-what-is-the-us-mediation-plan-in-libya?traffic_source=rss",
      "published": "2026-07-08T19:04:52+00:00",
      "compound": 0.3818,
      "label": "positive",
      "entities": [
        "Donald Trump"
      ]
    },
    {
      "title": "IDF says Oct. 7 terrorist eliminated; 5 said killed in Gaza strikes, including child",
      "source": "Times of Israel",
      "url": "https://www.timesofisrael.com/idf-says-oct-7-terrorist-eliminated-5-said-killed-in-gaza-strikes-including-child/",
      "published": "2026-07-08T19:03:10+00:00",
      "compound": -0.9819,
      "label": "negative",
      "entities": [
        "IDF",
        "Israel"
      ]
    },
    {
      "title": "Germany urges US-Iran negotiations, offers to minesweep Hormuz",
      "source": "Al Jazeera",
      "url": "https://www.aljazeera.com/video/newsfeed/2026/7/8/germany-urges-us-iran-negotiations-offers-to-minesweep-hormuz?traffic_source=rss",
      "published": "2026-07-08T18:57:41+00:00",
      "compound": 0.0,
      "label": "neutral",
      "entities": [
        "Iran",
        "Strait of Hormuz"
      ]
    },
    {
      "title": "Trump’s Iran strike comments shake markets, Brent crude hits two-week high",
      "source": "Al Jazeera",
      "url": "https://www.aljazeera.com/economy/2026/7/8/trumps-iran-strike-comments-shake-markets-brent-crude-hits-two-week-high?traffic_source=rss",
      "published": "2026-07-08T18:53:23+00:00",
      "compound": 0.1027,
      "label": "positive",
      "entities": [
        "Donald Trump",
        "Iran"
      ]
    },
    {
      "title": "Man sets wheelchair user in flames with Molotov cocktail",
      "source": "Al Jazeera",
      "url": "https://www.aljazeera.com/video/newsfeed/2026/7/8/man-sets-wheelchair-user-in-flames-with-molotov-cocktail?traffic_source=rss",
      "published": "2026-07-08T18:42:11+00:00",
      "compound": -0.34,
      "label": "negative",
      "entities": []
    },
    {
      "title": "Trump says he thinks Israel will withdraw troops from southern Lebanon",
      "source": "Al-Monitor",
      "url": "https://news.google.com/rss/articles/CBMirwFBVV95cUxNTE9xdThWYXBWbXo1dExQdzZjcmZRNS1Bc3M5RU1uV2RWcDE4Wk9TcElhVlBQMklIekRfX2ZoaS1fUnFxR3BabTE4OUFYWlNWbktmS0hnOC1vYkRUckdqTS1FbmZNX0ROcHBoUUUxUkUwbV9Ec3J6OTRZbHRGclkxUGZEeDNMWTd0ZDV6MTNyS0hBWWdEcF9nSlFwb2NleEJvbFRrenZHTzRtSnV4RjdJ?oc=5",
      "published": "2026-07-08T18:38:01+00:00",
      "compound": 0.0,
      "label": "neutral",
      "entities": [
        "Donald Trump",
        "Israel"
      ]
    },
    {
      "title": "Bowen: For all his bluster, Trump has no better option than talks with Iran",
      "source": "BBC",
      "url": "https://www.bbc.co.uk/news/articles/cy8we3j14ndo?at_medium=RSS&at_campaign=rss",
      "published": "2026-07-08T18:30:00+00:00",
      "compound": -0.2514,
      "label": "negative",
      "entities": [
        "Donald Trump",
        "Iran"
      ]
    },
    {
      "title": "FIFA World Cup: Quarterfinal brackets, match schedule and game previews",
      "source": "Al Jazeera",
      "url": "https://www.aljazeera.com/sports/2026/7/8/fifa-world-cup-2026-quarterfinal-fixtures-match-previews-schedule?traffic_source=rss",
      "published": "2026-07-08T18:27:17+00:00",
      "compound": 0.5423,
      "label": "positive",
      "entities": []
    },
    {
      "title": "Zelenskyy seeks NATO support as Russia continues attacks",
      "source": "Al Jazeera",
      "url": "https://www.aljazeera.com/video/newsfeed/2026/7/8/zelenskyy-seeks-nato-support-as-russia-continues-attacks?traffic_source=rss",
      "published": "2026-07-08T18:18:30+00:00",
      "compound": -0.0516,
      "label": "negative",
      "entities": []
    },
    {
      "title": "Oil prices rise sharply after Iran launches attacks on tankers near strait of Hormuz",
      "source": "The Guardian",
      "url": "https://news.google.com/rss/articles/CBMinwFBVV95cUxOTHZCN0g1UHJ1czVIT1dORUI2RW1sWWhYVFBrWFlCSlZaRFdjYW5STG9vMzZxZ1lGcUhubEdoV1Q5NFJTM1A3NnIzQ0pkM3VkazlycmdqLWpRRHEwRzdhc3J3M2RsSGlRNVh0Tk5MQ1dGUXliWk9PWkdzcV9JNHlEMnA4ZFB3empYN2x3VG5DZmFhbHdUUTlUbUZlVFBYbkk?oc=5",
      "published": "2026-07-08T18:18:00+00:00",
      "compound": -0.7003,
      "label": "negative",
      "entities": [
        "Iran",
        "Strait of Hormuz"
      ]
    },
    {
      "title": "Only 15% of Israelis believe Israel won war with Iran, survey finds",
      "source": "The Jerusalem Post",
      "url": "https://news.google.com/rss/articles/CBMiXEFVX3lxTE5ORDh5NDdZanU2Qm00U0RmclA3WF90Q2toV0hrMDB1eW0tamxsblJWbUVKMEpvT1NLbEpJZEs2dGM4c1ZFVFA5RkVoN2dtcXlIQWVIcThhOFA2ZzFp?oc=5",
      "published": "2026-07-08T18:17:42+00:00",
      "compound": -0.1027,
      "label": "negative",
      "entities": [
        "Iran",
        "Israel",
        "Jerusalem"
      ]
    },
    {
      "title": "Teenager arrested after two girls, 13, seriously injured in German school attack",
      "source": "BBC",
      "url": "https://www.bbc.co.uk/news/articles/c0qyvkgndzpo?at_medium=RSS&at_campaign=rss",
      "published": "2026-07-08T18:09:08+00:00",
      "compound": -0.8625,
      "label": "negative",
      "entities": []
    },
    {
      "title": "Greetings from a Syrian church, infused with a mix of sweet fruit and diverse faiths",
      "source": "NPR",
      "url": "https://www.npr.org/2026/07/08/nx-s1-5884694/syria-church-interfaith-fruit",
      "published": "2026-07-08T18:05:34+00:00",
      "compound": 0.8225,
      "label": "positive",
      "entities": []
    },
    {
      "title": "Israel watches as U.S.-Iran tensions escalate",
      "source": "CNN",
      "url": "https://news.google.com/rss/articles/CBMiogFBVV95cUxNbFczUUdsS2gwT1RBemNpLXFjSnZhd0ZyOUdoUFNmUjlaMDdQdUJ2QmNUOUhaRWwxUnV4c2ZLVE9CRlpkMmROb1VXbjB4aTc3a09zRVdqUGFSN183NHdwbk9XaVpoRUNzVVE3bUVKVENNVTNYOXoyX29YeUgzNUdaMjA2Q1c5WjRZVFV0Sl9CSzBsREVxNmdxMTFwVHVjUlFBb1E?oc=5",
      "published": "2026-07-08T18:00:25+00:00",
      "compound": -0.6597,
      "label": "negative",
      "entities": [
        "Iran",
        "Israel"
      ]
    },
    {
      "title": "Khamenei's coffin carried through Shia shrines as ceremonies held in Iraq",
      "source": "BBC",
      "url": "https://www.bbc.co.uk/news/articles/cp9le3kjj8eo?at_medium=RSS&at_campaign=rss",
      "published": "2026-07-08T17:56:24+00:00",
      "compound": 0.2732,
      "label": "positive",
      "entities": [
        "Khamenei",
        "Iran"
      ]
    },
    {
      "title": "Why have 100,000 people been signed off work with ADHD in the UK?",
      "source": "Al Jazeera",
      "url": "https://www.aljazeera.com/news/2026/7/8/why-have-100000-people-been-signed-off-work-with-adhd-in-the-uk?traffic_source=rss",
      "published": "2026-07-08T17:44:08+00:00",
      "compound": 0.3818,
      "label": "positive",
      "entities": []
    },
    {
      "title": "Israel braces for renewed Iran fighting as Netanyahu, Katz cancel military ceremony",
      "source": "Ynetnews",
      "url": "https://news.google.com/rss/articles/CBMiVkFVX3lxTE9Vc2VteG85WkR1d3VMdVNxV0xpaDFYRGcwWm1EVXZqUzEtX3BXcU5hR0lUQm51X0tKRVNDVmR5MGR0MG5tNjdFTGkta1Y0RW9oR3Rrb2FR?oc=5",
      "published": "2026-07-08T17:41:50+00:00",
      "compound": -0.7906,
      "label": "negative",
      "entities": [
        "Benjamin Netanyahu",
        "Iran",
        "Israel"
      ]
    },
    {
      "title": "Trump: Iran MOU is over, ‘we’ll hit them hard again tonight,’ but talks with ‘scum’ Tehran can continue",
      "source": "Times of Israel",
      "url": "https://www.timesofisrael.com/trump-iran-mou-is-over-well-hit-them-hard-again-tonight-but-talks-can-continue/",
      "published": "2026-07-08T17:34:39+00:00",
      "compound": -0.8537,
      "label": "negative",
      "entities": [
        "Khamenei",
        "Donald Trump",
        "Iran",
        "Israel",
        "Tehran"
      ]
    },
    {
      "title": "Is an Iran deal ‘over’ and war back on? A timeline of the conflict and talks",
      "source": "ABC News - Breaking News, Latest News and Videos",
      "url": "https://news.google.com/rss/articles/CBMijgFBVV95cUxPUDQ1LVVrS3hnZ19sUXBRaWJaUk1hUHJ3eDA4aWlpbHhJckNkQ2R4TGZvdmQ2ZVJTVUpxQlFJMWpiNUU1MTd2NVZhOXZSYTBLSGcwWU1tY29RSV9DMEVmSHlBRTRkZFpJT2MyZmVxN0tYUDN1ZThUeWdiWnRWcnNPb0JzLXRCUHlvbXFsTjNR0gGTAUFVX3lxTFBNVVhCMVZEZ2Nld1BLREJrbGxlcjlKQkVobUtjM3ozeTFoa1BPS3llWHZYLXR2dEhnQ3JXYlgzUnllZzhfbzJlQUZzZWx1RWg5cWFSWDB4MENjOWp2LTF0NjZJdzkwNGstMmlOSjQzRkV6YXlQOVJheklNd1BMYU5kR3pxSmw1YXA1eFgyMnc1QXV2TQ?oc=5",
      "published": "2026-07-08T17:34:11+00:00",
      "compound": -0.9146,
      "label": "negative",
      "entities": [
        "Iran"
      ]
    },
    {
      "title": "Pentagon Considers Relocating Gulf Bases to Israel",
      "source": "Democracy Now!",
      "url": "https://news.google.com/rss/articles/CBMinwFBVV95cUxOM1hPeDlaM0thak5nNlFPZHRiaV9KTmktM3FzS1ZWeC05NGtEV2MwVkprOTVQQzIxcjZ5ekgxd0xRWjFkdGNzbjUtRWQxNW5JWVVpd0Q5eWdvTVpyUm9DT3ZSaFpRa0ljYl83QU90WTQ2OG84Y1FldVFRNUJGbFR4UUZldktSdF9FeGZPelI4bXBxa3lLSkpocERuM0E5TjA?oc=5",
      "published": "2026-07-08T17:26:21+00:00",
      "compound": 0.0,
      "label": "neutral",
      "entities": [
        "Israel",
        "United States"
      ]
    },
    {
      "title": "German doctor jailed for murder of 15 patients and suspected of more",
      "source": "BBC",
      "url": "https://www.bbc.co.uk/news/articles/cq819jyp2g7o?at_medium=RSS&at_campaign=rss",
      "published": "2026-07-08T17:25:25+00:00",
      "compound": -0.9022,
      "label": "negative",
      "entities": []
    },
    {
      "title": "Trump on Iran: ‘We’ll probably hit them hard again tonight’",
      "source": "Al Jazeera",
      "url": "https://www.aljazeera.com/video/newsfeed/2026/7/8/trump-on-iran-well-probably-hit-them-hard-again?traffic_source=rss",
      "published": "2026-07-08T17:20:03+00:00",
      "compound": -0.4404,
      "label": "negative",
      "entities": [
        "Donald Trump",
        "Iran"
      ]
    },
    {
      "title": "‘Down with the USA’: US influencer Jackson Hinkle attends Khamenei’s funera",
      "source": "Al Jazeera",
      "url": "https://www.aljazeera.com/video/newsfeed/2026/7/8/down-with-the-usa-us-influencer-jackson-hinkle-attends-khameneis-funera?traffic_source=rss",
      "published": "2026-07-08T17:17:23+00:00",
      "compound": -0.3612,
      "label": "negative",
      "entities": [
        "Khamenei"
      ]
    },
    {
      "title": "Trump says peace deal with Iran is over after sides exchange strikes",
      "source": "CBC",
      "url": "https://news.google.com/rss/articles/CBMiiAFBVV95cUxPR0JDNDBOblQ5ZXlOb25QTEtJdzdITV81STFoS3IzaXR5WE53R19TQ0ZGdC1NaGJjczd5NEt0dy0xSExuVC10eUNQRUR1UlIwSjJBRldjSEFhZXM1XzRFclpjOWZMQUpOUk1xMzVkOFUyZWNTUThaWmk3NEowRzIxR0ZBbG5KZktk?oc=5",
      "published": "2026-07-08T17:16:24+00:00",
      "compound": 0.4588,
      "label": "positive",
      "entities": [
        "Donald Trump",
        "Iran"
      ]
    },
    {
      "title": "A plea to the prime minister: Heed the lessons of our history in this land, and pull back from the brink",
      "source": "Times of Israel",
      "url": "https://www.timesofisrael.com/a-plea-to-the-prime-minister-heed-the-lessons-of-our-history-in-this-land-and-pull-back-from-the-brink/",
      "published": "2026-07-08T17:07:10+00:00",
      "compound": 0.631,
      "label": "positive",
      "entities": [
        "Israel"
      ]
    },
    {
      "title": "Eight killed after landslide hits girls' school in Bangladesh",
      "source": "BBC",
      "url": "https://www.bbc.co.uk/news/articles/cx2wkzww20ro?at_medium=RSS&at_campaign=rss",
      "published": "2026-07-08T17:02:54+00:00",
      "compound": -0.6705,
      "label": "negative",
      "entities": []
    }
  ]
}